{"data": {"series": [{"chartTooltipContent": "%y.# %ly o godz. %x", "paramLabel": "Dwutlenek azotu", "label": "Dwutlenek azotu", "aggType": "A1h", "decimals": 0, "avg": {"min": null, "avg": null, "max": null}, "retroCount": 2, "scaleMax": null, "paramId": "no2", "unit": "ug/m3", "paramCode": "NO<sub>2</sub>", "thresholds": {"atDecimals": 0, "at": 400, "tv": null, "it": null, "itDecimals": 0, "lv": 200, "lvDecimals": 0, "tvDecimals": 0}, "ord": 2, "isAvgValid": false, "data": [["1270504800", "16"], ["1270508400", "11"], ["1270512000", "10"], ["1270515600", "10"], ["1270519200", "10"], ["1270522800", "12"], ["1270526400", "17"], ["1270530000", "22"], ["1270533600", "31"], ["1270537200", "31"], ["1270540800", "32"], ["1270544400", "31"]], "extStartTime": 1270504800, "measType": "auto", "interval": 3600, "thresholdsForAvg": {"min": null, "avg": null, "max": null}, "scaleMin": null, "coverageRate": 0.75, "paramPostfix": "", "count": 24, "unitLabel": "&micro;g/m<sup>3</sup>", "startTime": 1270512000}, {"chartTooltipContent": "%y.# %ly o godz. %x", "paramLabel": "Dwutlenek siarki", "label": "Dwutlenek siarki<sup>3)</sup>", "aggType": "A1h", "decimals": 1, "avg": {"min": "1", "avg": 5, "max": "13"}, "retroCount": 2, "scaleMax": null, "paramId": "so2", "unit": "ug/m3", "paramCode": "SO<sub>2</sub>", "thresholds": {"atDecimals": 0, "at": 500, "tv": null, "it": null, "itDecimals": 0, "lv": 350, "lvDecimals": 0, "tvDecimals": 0}, "ord": 1, "isAvgValid": true, "data": [["1270504800", "2"], ["1270508400", "2"], ["1270512000", "2"], ["1270515600", "1"], ["1270519200", "2"], ["1270522800", "3"], ["1270526400", "3"], ["1270530000", "1"], ["1270533600", "2"], ["1270537200", "3"], ["1270540800", "4"], ["1270544400", "6"], ["1270555200", "5"], ["1270566000", "6"], ["1270569600", "4"], ["1270573200", "5"], ["1270576800", "5"], ["1270580400", "6"], ["1270587600", "13"], ["1270591200", "13"], ["1270594800", "11"]], "extStartTime": 1270504800, "measType": "auto", "interval": 3600, "thresholdsForAvg": {"min": null, "avg": {"atDecimals": 0, "at": null, "tv": null, "it": null, "itDecimals": 0, "lv": 125, "lvDecimals": 0, "tvDecimals": 0}, "max": null}, "scaleMin": null, "coverageRate": 0.75, "paramPostfix": "<sup>3)</sup>", "count": 24, "unitLabel": "&micro;g/m<sup>3</sup>", "startTime": 1270512000}, {"chartTooltipContent": "%y.# %ly o godz. %x", "paramLabel": "Ozon", "label": "Ozon", "aggType": "A1h", "decimals": 0, "avg": {"min": "14", "avg": 45.090909090909, "max": "71"}, "retroCount": 2, "scaleMax": null, "paramId": "o3", "unit": "ug/m3", "paramCode": "O<sub>3</sub>", "thresholds": {"atDecimals": 0, "at": 240, "tv": null, "it": 180, "itDecimals": 0, "lv": null, "lvDecimals": 0, "tvDecimals": 0}, "ord": 4, "isAvgValid": true, "data": [["1270504800", "67"], ["1270508400", "72"], ["1270512000", "68"], ["1270515600", "61"], ["1270519200", "60"], ["1270522800", "63"], ["1270526400", "71"], ["1270530000", "67"], ["1270533600", "55"], ["1270537200", "50"], ["1270540800", "46"], ["1270544400", "42"], ["1270555200", "41"], ["1270558800", "42"], ["1270562400", "53"], ["1270566000", "56"], ["1270569600", "44"], ["1270573200", "34"], ["1270576800", "30"], ["1270580400", "14"], ["1270584000", "26"], ["1270587600", "25"], ["1270591200", "23"], ["1270594800", "21"]], "extStartTime": 1270504800, "measType": "auto", "interval": 3600, "thresholdsForAvg": {"min": null, "avg": null, "max": null}, "scaleMin": null, "coverageRate": 0.75, "paramPostfix": "", "count": 24, "unitLabel": "&micro;g/m<sup>3</sup>", "startTime": 1270512000}, {"chartTooltipContent": "%y.# %ly o godz. %x", "paramLabel": "Ozon", "label": "Ozon 8h<sup>2)</sup>", "aggType": "sA8h", "decimals": 0, "avg": {"min": null, "avg": null, "max": null}, "retroCount": 2, "scaleMax": null, "paramId": "o3", "unit": "ug/m3", "paramCode": "O<sub>3</sub>", "thresholds": {"atDecimals": 0, "at": null, "tv": 120, "it": null, "itDecimals": 0, "lv": null, "lvDecimals": 0, "tvDecimals": 0}, "ord": 4, "isAvgValid": false, "data": [], "extStartTime": 1270504800, "measType": "auto", "interval": 3600, "thresholdsForAvg": {"min": null, "avg": null, "max": {"atDecimals": 0, "at": null, "tv": 120, "it": null, "itDecimals": 0, "lv": null, "lvDecimals": 0, "tvDecimals": 0}}, "scaleMin": null, "coverageRate": 0.75, "paramPostfix": " 8h<sup>2)</sup>", "count": 24, "unitLabel": "&micro;g/m<sup>3</sup>", "startTime": 1270512000}, {"chartTooltipContent": "%y.# %ly o godz. %x", "paramLabel": "Py\u0142 zawieszony PM10", "label": "Py\u0142 zawieszony PM10", "aggType": "A1h", "decimals": 0, "avg": {"min": null, "avg": null, "max": null}, "retroCount": 2, "scaleMax": null, "paramId": "pm10", "unit": "ug/m3", "paramCode": "PM10", "thresholds": {"atDecimals": 0, "at": null, "tv": null, "it": null, "itDecimals": 0, "lv": null, "lvDecimals": 0, "tvDecimals": 0}, "ord": 7, "isAvgValid": false, "data": [["1270558800", "32"], ["1270562400", "25"], ["1270566000", "27"], ["1270569600", "36"], ["1270573200", "44"], ["1270576800", "37"], ["1270580400", "55"], ["1270584000", "59"], ["1270587600", "56"], ["1270591200", "51"], ["1270594800", "45"]], "extStartTime": 1270504800, "measType": "auto", "interval": 3600, "thresholdsForAvg": {"min": null, "avg": {"atDecimals": 0, "at": 300, "tv": null, "it": 200, "itDecimals": 0, "lv": 50, "lvDecimals": 0, "tvDecimals": 0}, "max": null}, "scaleMin": null, "coverageRate": 0.75, "paramPostfix": "", "count": 24, "unitLabel": "&micro;g/m<sup>3</sup>", "startTime": 1270512000}, {"chartTooltipContent": "%y.# %ly o godz. %x", "paramLabel": "Py\u0142 zawieszony PM2.5", "label": "Py\u0142 zawieszony PM2.5", "aggType": "A1h", "decimals": 0, "avg": {"min": "9", "avg": 24.25, "max": "49"}, "retroCount": 2, "scaleMax": null, "paramId": "pm2.5", "unit": "ug/m3", "paramCode": "PM2.5", "thresholds": {"atDecimals": 0, "at": null, "tv": null, "it": null, "itDecimals": 0, "lv": null, "lvDecimals": 0, "tvDecimals": 0}, "ord": 8, "isAvgValid": true, "data": [["1270504800", "9"], ["1270508400", "9"], ["1270512000", "13"], ["1270515600", "12"], ["1270519200", "10"], ["1270522800", "9"], ["1270526400", "11"], ["1270530000", "12"], ["1270533600", "13"], ["1270537200", "14"], ["1270540800", "22"], ["1270544400", "28"], ["1270548000", "27"], ["1270551600", "27"], ["1270555200", "25"], ["1270558800", "28"], ["1270562400", "25"], ["1270566000", "22"], ["1270569600", "25"], ["1270573200", "25"], ["1270576800", "24"], ["1270580400", "38"], ["1270584000", "47"], ["1270587600", "49"], ["1270591200", "39"], ["1270594800", "37"]], "extStartTime": 1270504800, "measType": "auto", "interval": 3600, "thresholdsForAvg": {"min": null, "avg": null, "max": null}, "scaleMin": null, "coverageRate": 0.75, "paramPostfix": "", "count": 24, "unitLabel": "&micro;g/m<sup>3</sup>", "startTime": 1270512000}, {"chartTooltipContent": "%y.# %ly o godz. %x", "paramLabel": "Tlenek azotu", "label": "Tlenek azotu", "aggType": "A1h", "decimals": 0, "avg": {"min": null, "avg": null, "max": null}, "retroCount": 2, "scaleMax": null, "paramId": "no", "unit": "ug/m3", "paramCode": "NO", "thresholds": null, "ord": 14, "isAvgValid": false, "data": [["1270504800", "3"], ["1270508400", "2"], ["1270512000", "2"], ["1270515600", "2"], ["1270519200", "2"], ["1270522800", "2"], ["1270526400", "5"], ["1270530000", "6"], ["1270533600", "9"], ["1270537200", "8"], ["1270540800", "10"], ["1270544400", "9"]], "extStartTime": 1270504800, "measType": "auto", "interval": 3600, "thresholdsForAvg": {"min": null, "avg": null, "max": null}, "scaleMin": null, "coverageRate": 0.75, "paramPostfix": "", "count": 24, "unitLabel": "&micro;g/m<sup>3</sup>", "startTime": 1270512000}, {"chartTooltipContent": "%y.# %ly o godz. %x", "paramLabel": "Tlenki azotu", "label": "Tlenki azotu", "aggType": "A1h", "decimals": 0, "avg": {"min": null, "avg": null, "max": null}, "retroCount": 2, "scaleMax": null, "paramId": "nox", "unit": "ug/m3", "paramCode": "NO<sub>x</sub>", "thresholds": null, "ord": 3, "isAvgValid": false, "data": [["1270504800", "19"], ["1270508400", "14"], ["1270512000", "13"], ["1270515600", "14"], ["1270519200", "13"], ["1270522800", "15"], ["1270526400", "24"], ["1270530000", "30"], ["1270533600", "45"], ["1270537200", "43"], ["1270540800", "46"], ["1270544400", "44"]], "extStartTime": 1270504800, "measType": "auto", "interval": 3600, "thresholdsForAvg": {"min": null, "avg": null, "max": null}, "scaleMin": null, "coverageRate": 0.75, "paramPostfix": "", "count": 24, "unitLabel": "&micro;g/m<sup>3</sup>", "startTime": 1270512000}], "charts": [], "viewType": "station", "title": "Dane pomiarowe dla stacji Krak\u00f3w-Kurdwan\u00f3w w dniu 06.04.2010 r.", "dateFormat": "H:00", "unitLabel": "&micro;g/m<sup>3</sup>"}, "success": true}