{"data": {"series": [{"chartTooltipContent": "%y.# %ly o godz. %x", "paramLabel": "Dwutlenek azotu", "label": "Dwutlenek azotu", "aggType": "A1h", "decimals": 0, "avg": {"min": "13.7996", "avg": 35.284152173913, "max": "76.1842"}, "retroCount": 2, "scaleMax": null, "paramId": "no2", "unit": "ug/m3", "paramCode": "NO<sub>2</sub>", "thresholds": {"atDecimals": 0, "at": 400, "tv": null, "it": null, "itDecimals": 0, "lv": 200, "lvDecimals": 0, "tvDecimals": 0}, "ord": 2, "isAvgValid": true, "data": [["1436306400", "101.552"], ["1436310000", "85.2502"], ["1436313600", "76.1842"], ["1436317200", "56.1327"], ["1436320800", "59.9529"], ["1436324400", "60.3674"], ["1436328000", "51.5011"], ["1436331600", "15.4092"], ["1436335200", "32.6517"], ["1436338800", "36.7493"], ["1436342400", "39.1745"], ["1436346000", "52.582"], ["1436349600", "31.7276"], ["1436356800", "15.6505"], ["1436360400", "17.6262"], ["1436364000", "18.0407"], ["1436367600", "15.1712"], ["1436371200", "17.9471"], ["1436374800", "24.7579"], ["1436378400", "48.451"], ["1436382000", "39.4445"], ["1436385600", "42.3761"], ["1436389200", "31.9221"], ["1436392800", "13.7996"], ["1436396400", "13.916"]], "extStartTime": 1436306400, "measType": "auto", "interval": 3600, "thresholdsForAvg": {"min": null, "avg": null, "max": null}, "scaleMin": null, "coverageRate": 0.75, "paramPostfix": "", "count": 24, "unitLabel": "&micro;g/m<sup>3</sup>", "startTime": 1436313600}, {"chartTooltipContent": "%y.# %ly o godz. %x", "paramLabel": "Dwutlenek siarki", "label": "Dwutlenek siarki<sup>3)</sup>", "aggType": "A1h", "decimals": 1, "avg": {"min": "2.139", "avg": 2.3922882608696, "max": "2.66106"}, "retroCount": 2, "scaleMax": null, "paramId": "so2", "unit": "ug/m3", "paramCode": "SO<sub>2</sub>", "thresholds": {"atDecimals": 0, "at": 500, "tv": null, "it": null, "itDecimals": 0, "lv": 350, "lvDecimals": 0, "tvDecimals": 0}, "ord": 1, "isAvgValid": true, "data": [["1436306400", "3.03034"], ["1436310000", "3.09579"], ["1436313600", "2.52175"], ["1436317200", "2.2731"], ["1436320800", "2.66106"], ["1436324400", "2.52141"], ["1436328000", "2.14235"], ["1436331600", "2.51458"], ["1436335200", "2.19775"], ["1436338800", "2.44564"], ["1436342400", "2.48873"], ["1436346000", "2.42719"], ["1436349600", "2.43392"], ["1436356800", "2.57685"], ["1436360400", "2.46953"], ["1436364000", "2.33639"], ["1436367600", "2.55466"], ["1436371200", "2.50465"], ["1436374800", "2.139"], ["1436378400", "2.33126"], ["1436382000", "2.42891"], ["1436385600", "2.33038"], ["1436389200", "2.25287"], ["1436392800", "2.19018"], ["1436396400", "2.28047"]], "extStartTime": 1436306400, "measType": "auto", "interval": 3600, "thresholdsForAvg": {"min": null, "avg": {"atDecimals": 0, "at": null, "tv": null, "it": null, "itDecimals": 0, "lv": 125, "lvDecimals": 0, "tvDecimals": 0}, "max": null}, "scaleMin": null, "coverageRate": 0.75, "paramPostfix": "<sup>3)</sup>", "count": 24, "unitLabel": "&micro;g/m<sup>3</sup>", "startTime": 1436313600}, {"chartTooltipContent": "%y.# %ly o godz. %x", "paramLabel": "Ozon", "label": "Ozon", "aggType": "A1h", "decimals": 0, "avg": {"min": "4.91092", "avg": 51.652602916667, "max": "120.057"}, "retroCount": 2, "scaleMax": null, "paramId": "o3", "unit": "ug/m3", "paramCode": "O<sub>3</sub>", "thresholds": {"atDecimals": 0, "at": 240, "tv": null, "it": 180, "itDecimals": 0, "lv": null, "lvDecimals": 0, "tvDecimals": 0}, "ord": 4, "isAvgValid": true, "data": [["1436306400", "7.27936"], ["1436310000", "5.75213"], ["1436313600", "6.53626"], ["1436317200", "16.6946"], ["1436320800", "6.15129"], ["1436324400", "4.91092"], ["1436328000", "21.0802"], ["1436331600", "90.5624"], ["1436335200", "58.4835"], ["1436338800", "53.0757"], ["1436342400", "49.5685"], ["1436346000", "30.2249"], ["1436349600", "61.4101"], ["1436353200", "100.073"], ["1436356800", "120.057"], ["1436360400", "106.058"], ["1436364000", "89.7414"], ["1436367600", "81.8656"], ["1436371200", "77.7779"], ["1436374800", "70.4083"], ["1436378400", "33.0174"], ["1436382000", "32.5223"], ["1436385600", "21.5281"], ["1436389200", "26.6107"], ["1436392800", "42.4531"], ["1436396400", "38.8513"]], "extStartTime": 1436306400, "measType": "auto", "interval": 3600, "thresholdsForAvg": {"min": null, "avg": null, "max": null}, "scaleMin": null, "coverageRate": 0.75, "paramPostfix": "", "count": 24, "unitLabel": "&micro;g/m<sup>3</sup>", "startTime": 1436313600}, {"chartTooltipContent": "%y.# %ly o godz. %x", "paramLabel": "Ozon", "label": "Ozon 8h<sup>2)</sup>", "aggType": "sA8h", "decimals": 0, "avg": {"min": "10.8109", "avg": 54.237320833333, "max": "88.4239"}, "retroCount": 2, "scaleMax": null, "paramId": "o3", "unit": "ug/m3", "paramCode": "O<sub>3</sub>", "thresholds": {"atDecimals": 0, "at": null, "tv": 120, "it": null, "itDecimals": 0, "lv": null, "lvDecimals": 0, "tvDecimals": 0}, "ord": 4, "isAvgValid": true, "data": [["1436306400", "107.823"], ["1436310000", "90.5707"], ["1436313600", "73.457"], ["1436317200", "56.6026"], ["1436320800", "37.9554"], ["1436324400", "21.943"], ["1436328000", "10.8109"], ["1436331600", "19.8709"], ["1436335200", "26.2714"], ["1436338800", "32.1869"], ["1436342400", "37.5659"], ["1436346000", "39.2572"], ["1436349600", "46.1645"], ["1436353200", "58.0598"], ["1436356800", "70.4319"], ["1436360400", "72.3688"], ["1436364000", "76.2761"], ["1436367600", "79.8748"], ["1436371200", "83.401"], ["1436374800", "88.4239"], ["1436378400", "84.8748"], ["1436382000", "76.431"], ["1436385600", "64.1149"], ["1436389200", "54.184"], ["1436392800", "48.2729"], ["1436396400", "42.8961"]], "extStartTime": 1436306400, "measType": "auto", "interval": 3600, "thresholdsForAvg": {"min": null, "avg": null, "max": {"atDecimals": 0, "at": null, "tv": 120, "it": null, "itDecimals": 0, "lv": null, "lvDecimals": 0, "tvDecimals": 0}}, "scaleMin": null, "coverageRate": 0.75, "paramPostfix": " 8h<sup>2)</sup>", "count": 24, "unitLabel": "&micro;g/m<sup>3</sup>", "startTime": 1436313600}, {"chartTooltipContent": "%y.# %ly o godz. %x", "paramLabel": "Py\u0142 zawieszony PM10", "label": "Py\u0142 zawieszony PM10", "aggType": "A1h", "decimals": 0, "avg": {"min": "4.32562", "avg": 21.988009545455, "max": "86.8126"}, "retroCount": 2, "scaleMax": null, "paramId": "pm10", "unit": "ug/m3", "paramCode": "PM10", "thresholds": {"atDecimals": 0, "at": null, "tv": null, "it": null, "itDecimals": 0, "lv": null, "lvDecimals": 0, "tvDecimals": 0}, "ord": 7, "isAvgValid": true, "data": [["1436306400", "41.3357"], ["1436310000", "44.4098"], ["1436313600", "31.5916"], ["1436317200", "26.5041"], ["1436320800", "30.4947"], ["1436324400", "30.0501"], ["1436328000", "86.8126"], ["1436331600", "13.7637"], ["1436335200", "11.5672"], ["1436338800", "8.47641"], ["1436342400", "8.75746"], ["1436346000", "13.2261"], ["1436349600", "25.8277"], ["1436360400", "58.7731"], ["1436364000", "19.5289"], ["1436367600", "19.9313"], ["1436371200", "13.1093"], ["1436374800", "23.7781"], ["1436378400", "10.6509"], ["1436382000", "6.66508"], ["1436385600", "4.32562"], ["1436389200", "17.9487"], ["1436392800", "12.4513"], ["1436396400", "9.50224"]], "extStartTime": 1436306400, "measType": "auto", "interval": 3600, "thresholdsForAvg": {"min": null, "avg": {"atDecimals": 0, "at": 300, "tv": null, "it": 200, "itDecimals": 0, "lv": 50, "lvDecimals": 0, "tvDecimals": 0}, "max": null}, "scaleMin": null, "coverageRate": 0.75, "paramPostfix": "", "count": 24, "unitLabel": "&micro;g/m<sup>3</sup>", "startTime": 1436313600}, {"chartTooltipContent": "%y.# %ly o godz. %x", "paramLabel": "Py\u0142 zawieszony PM2.5", "label": "Py\u0142 zawieszony PM2.5", "aggType": "A1h", "decimals": 0, "avg": {"min": "3", "avg": 11.534083333333, "max": "35.7"}, "retroCount": 2, "scaleMax": null, "paramId": "pm2.5", "unit": "ug/m3", "paramCode": "PM2.5", "thresholds": {"atDecimals": 0, "at": null, "tv": null, "it": null, "itDecimals": 0, "lv": null, "lvDecimals": 0, "tvDecimals": 0}, "ord": 8, "isAvgValid": true, "data": [["1436306400", "28"], ["1436310000", "32.2"], ["1436313600", "25.5"], ["1436317200", "25.9"], ["1436320800", "23.6"], ["1436324400", "25"], ["1436328000", "35.7"], ["1436331600", "4.5"], ["1436335200", "4.5"], ["1436338800", "4.5"], ["1436342400", "4.5"], ["1436346000", "4.5"], ["1436349600", "24.994"], ["1436353200", "3"], ["1436356800", "3"], ["1436360400", "20.9"], ["1436364000", "11.5"], ["1436367600", "12"], ["1436371200", "5.8"], ["1436374800", "5.6"], ["1436378400", "9.1"], ["1436382000", "4.9"], ["1436385600", "3.924"], ["1436389200", "4.9"], ["1436392800", "4.5"], ["1436396400", "4.5"]], "extStartTime": 1436306400, "measType": "auto", "interval": 3600, "thresholdsForAvg": {"min": null, "avg": null, "max": null}, "scaleMin": null, "coverageRate": 0.75, "paramPostfix": "", "count": 24, "unitLabel": "&micro;g/m<sup>3</sup>", "startTime": 1436313600}, {"chartTooltipContent": "%y.# %ly o godz. %x", "paramLabel": "Tlenek azotu", "label": "Tlenek azotu", "aggType": "A1h", "decimals": 0, "avg": {"min": "0.849054", "avg": 9.6127497391304, "max": "35.3625"}, "retroCount": 2, "scaleMax": null, "paramId": "no", "unit": "ug/m3", "paramCode": "NO", "thresholds": null, "ord": 14, "isAvgValid": true, "data": [["1436306400", "58.0479"], ["1436310000", "51.6764"], ["1436313600", "30.0825"], ["1436317200", "6.12698"], ["1436320800", "30.0628"], ["1436324400", "35.3625"], ["1436328000", "19.996"], ["1436331600", "1.2138"], ["1436335200", "4.69778"], ["1436338800", "6.95139"], ["1436342400", "10.2577"], ["1436346000", "18.004"], ["1436349600", "10.3706"], ["1436356800", "0.849054"], ["1436360400", "1.52901"], ["1436364000", "2.79507"], ["1436367600", "2.51484"], ["1436371200", "2.81931"], ["1436374800", "4.23362"], ["1436378400", "7.11107"], ["1436382000", "8.20289"], ["1436385600", "8.96148"], ["1436389200", "6.3653"], ["1436392800", "1.57231"], ["1436396400", "1.01324"]], "extStartTime": 1436306400, "measType": "auto", "interval": 3600, "thresholdsForAvg": {"min": null, "avg": null, "max": null}, "scaleMin": null, "coverageRate": 0.75, "paramPostfix": "", "count": 24, "unitLabel": "&micro;g/m<sup>3</sup>", "startTime": 1436313600}, {"chartTooltipContent": "%y.# %ly o godz. %x", "paramLabel": "Tlenki azotu", "label": "Tlenki azotu", "aggType": "A1h", "decimals": 0, "avg": {"min": "15.4", "avg": 49.913043478261, "max": "122"}, "retroCount": 2, "scaleMax": null, "paramId": "nox", "unit": "ug/m3", "paramCode": "NO<sub>x</sub>", "thresholds": null, "ord": 3, "isAvgValid": true, "data": [["1436306400", "189.8"], ["1436310000", "163.9"], ["1436313600", "122"], ["1436317200", "65.4"], ["1436320800", "105.8"], ["1436324400", "114.2"], ["1436328000", "81.9"], ["1436331600", "17.2"], ["1436335200", "39.8"], ["1436338800", "47.3"], ["1436342400", "54.9"], ["1436346000", "80"], ["1436349600", "47.5"], ["1436356800", "16.9"], ["1436360400", "19.9"], ["1436364000", "22.3"], ["1436367600", "19"], ["1436371200", "22.2"], ["1436374800", "31.2"], ["1436378400", "59.3"], ["1436382000", "51.9"], ["1436385600", "56.1"], ["1436389200", "41.6"], ["1436392800", "16.2"], ["1436396400", "15.4"]], "extStartTime": 1436306400, "measType": "auto", "interval": 3600, "thresholdsForAvg": {"min": null, "avg": null, "max": null}, "scaleMin": null, "coverageRate": 0.75, "paramPostfix": "", "count": 24, "unitLabel": "&micro;g/m<sup>3</sup>", "startTime": 1436313600}], "charts": [], "viewType": "station", "title": "Dane pomiarowe dla stacji Krak\u00f3w-Kurdwan\u00f3w w dniu 08.07.2015 r.", "dateFormat": "H:00", "unitLabel": "&micro;g/m<sup>3</sup>"}, "success": true}