{"data": {"series": [{"chartTooltipContent": "%y.# %ly o godz. %x", "paramLabel": "Dwutlenek azotu", "label": "Dwutlenek azotu", "aggType": "A1h", "decimals": 0, "avg": {"min": "19", "avg": 33.434782608696, "max": "64"}, "retroCount": 2, "scaleMax": null, "paramId": "no2", "unit": "ug/m3", "paramCode": "NO<sub>2</sub>", "thresholds": {"atDecimals": 0, "at": 400, "tv": null, "it": null, "itDecimals": 0, "lv": 200, "lvDecimals": 0, "tvDecimals": 0}, "ord": 2, "isAvgValid": true, "data": [["1319148000", "29"], ["1319151600", "28"], ["1319155200", "24"], ["1319158800", "22"], ["1319162400", "19"], ["1319166000", "20"], ["1319169600", "20"], ["1319173200", "24"], ["1319176800", "27"], ["1319180400", "35"], ["1319184000", "42"], ["1319187600", "32"], ["1319191200", "22"], ["1319194800", "23"], ["1319198400", "23"], ["1319202000", "30"], ["1319205600", "37"], ["1319209200", "48"], ["1319212800", "58"], ["1319216400", "64"], ["1319220000", "61"], ["1319227200", "47"], ["1319230800", "36"], ["1319234400", "30"], ["1319238000", "25"]], "extStartTime": 1319148000, "measType": "auto", "interval": 3600, "thresholdsForAvg": {"min": null, "avg": null, "max": null}, "scaleMin": null, "coverageRate": 0.75, "paramPostfix": "", "count": 24, "unitLabel": "&micro;g/m<sup>3</sup>", "startTime": 1319155200}, {"chartTooltipContent": "%y.# %ly o godz. %x", "paramLabel": "Dwutlenek siarki", "label": "Dwutlenek siarki<sup>3)</sup>", "aggType": "A1h", "decimals": 1, "avg": {"min": "1", "avg": 7.2608695652174, "max": "11"}, "retroCount": 2, "scaleMax": null, "paramId": "so2", "unit": "ug/m3", "paramCode": "SO<sub>2</sub>", "thresholds": {"atDecimals": 0, "at": 500, "tv": null, "it": null, "itDecimals": 0, "lv": 350, "lvDecimals": 0, "tvDecimals": 0}, "ord": 1, "isAvgValid": true, "data": [["1319148000", "4"], ["1319151600", "5"], ["1319155200", "5"], ["1319158800", "6"], ["1319162400", "7"], ["1319166000", "6"], ["1319169600", "8"], ["1319173200", "9"], ["1319176800", "9"], ["1319180400", "10"], ["1319184000", "11"], ["1319187600", "11"], ["1319191200", "11"], ["1319194800", "11"], ["1319198400", "11"], ["1319202000", "10"], ["1319205600", "8"], ["1319209200", "6"], ["1319216400", "1"], ["1319220000", "2"], ["1319223600", "2"], ["1319227200", "3"], ["1319230800", "5"], ["1319234400", "6"], ["1319238000", "9"]], "extStartTime": 1319148000, "measType": "auto", "interval": 3600, "thresholdsForAvg": {"min": null, "avg": {"atDecimals": 0, "at": null, "tv": null, "it": null, "itDecimals": 0, "lv": 125, "lvDecimals": 0, "tvDecimals": 0}, "max": null}, "scaleMin": null, "coverageRate": 0.75, "paramPostfix": "<sup>3)</sup>", "count": 24, "unitLabel": "&micro;g/m<sup>3</sup>", "startTime": 1319155200}, {"chartTooltipContent": "%y.# %ly o godz. %x", "paramLabel": "Ozon", "label": "Ozon", "aggType": "A1h", "decimals": 0, "avg": {"min": null, "avg": null, "max": null}, "retroCount": 2, "scaleMax": null, "paramId": "o3", "unit": "ug/m3", "paramCode": "O<sub>3</sub>", "thresholds": {"atDecimals": 0, "at": 240, "tv": null, "it": 180, "itDecimals": 0, "lv": null, "lvDecimals": 0, "tvDecimals": 0}, "ord": 4, "isAvgValid": false, "data": [], "extStartTime": 1319148000, "measType": "auto", "interval": 3600, "thresholdsForAvg": {"min": null, "avg": null, "max": null}, "scaleMin": null, "coverageRate": 0.75, "paramPostfix": "", "count": 24, "unitLabel": "&micro;g/m<sup>3</sup>", "startTime": 1319155200}, {"chartTooltipContent": "%y.# %ly o godz. %x", "paramLabel": "Ozon", "label": "Ozon 8h<sup>2)</sup>", "aggType": "sA8h", "decimals": 0, "avg": {"min": null, "avg": null, "max": null}, "retroCount": 2, "scaleMax": null, "paramId": "o3", "unit": "ug/m3", "paramCode": "O<sub>3</sub>", "thresholds": {"atDecimals": 0, "at": null, "tv": 120, "it": null, "itDecimals": 0, "lv": null, "lvDecimals": 0, "tvDecimals": 0}, "ord": 4, "isAvgValid": false, "data": [], "extStartTime": 1319148000, "measType": "auto", "interval": 3600, "thresholdsForAvg": {"min": null, "avg": null, "max": {"atDecimals": 0, "at": null, "tv": 120, "it": null, "itDecimals": 0, "lv": null, "lvDecimals": 0, "tvDecimals": 0}}, "scaleMin": null, "coverageRate": 0.75, "paramPostfix": " 8h<sup>2)</sup>", "count": 24, "unitLabel": "&micro;g/m<sup>3</sup>", "startTime": 1319155200}, {"chartTooltipContent": "%y.# %ly o godz. %x", "paramLabel": "Py\u0142 zawieszony PM10", "label": "Py\u0142 zawieszony PM10", "aggType": "A1h", "decimals": 0, "avg": {"min": "26", "avg": 66.95652173913, "max": "175"}, "retroCount": 2, "scaleMax": null, "paramId": "pm10", "unit": "ug/m3", "paramCode": "PM10", "thresholds": {"atDecimals": 0, "at": null, "tv": null, "it": null, "itDecimals": 0, "lv": null, "lvDecimals": 0, "tvDecimals": 0}, "ord": 7, "isAvgValid": true, "data": [["1319148000", "59"], ["1319151600", "66"], ["1319155200", "70"], ["1319158800", "63"], ["1319162400", "47"], ["1319166000", "50"], ["1319169600", "53"], ["1319173200", "58"], ["1319176800", "61"], ["1319180400", "61"], ["1319184000", "76"], ["1319187600", "46"], ["1319191200", "38"], ["1319194800", "34"], ["1319198400", "26"], ["1319202000", "26"], ["1319205600", "31"], ["1319209200", "33"], ["1319212800", "49"], ["1319216400", "73"], ["1319220000", "103"], ["1319227200", "175"], ["1319230800", "138"], ["1319234400", "117"], ["1319238000", "112"]], "extStartTime": 1319148000, "measType": "auto", "interval": 3600, "thresholdsForAvg": {"min": null, "avg": {"atDecimals": 0, "at": 300, "tv": null, "it": 200, "itDecimals": 0, "lv": 50, "lvDecimals": 0, "tvDecimals": 0}, "max": null}, "scaleMin": null, "coverageRate": 0.75, "paramPostfix": "", "count": 24, "unitLabel": "&micro;g/m<sup>3</sup>", "startTime": 1319155200}, {"chartTooltipContent": "%y.# %ly o godz. %x", "paramLabel": "Py\u0142 zawieszony PM2.5", "label": "Py\u0142 zawieszony PM2.5", "aggType": "A1h", "decimals": 0, "avg": {"min": "11", "avg": 36.75, "max": "89"}, "retroCount": 2, "scaleMax": null, "paramId": "pm2.5", "unit": "ug/m3", "paramCode": "PM2.5", "thresholds": {"atDecimals": 0, "at": null, "tv": null, "it": null, "itDecimals": 0, "lv": null, "lvDecimals": 0, "tvDecimals": 0}, "ord": 8, "isAvgValid": true, "data": [["1319148000", "32"], ["1319151600", "34"], ["1319155200", "37"], ["1319158800", "35"], ["1319162400", "30"], ["1319166000", "27"], ["1319169600", "30"], ["1319173200", "31"], ["1319176800", "33"], ["1319180400", "36"], ["1319184000", "38"], ["1319187600", "22"], ["1319191200", "18"], ["1319194800", "15"], ["1319198400", "11"], ["1319202000", "12"], ["1319205600", "12"], ["1319209200", "14"], ["1319212800", "20"], ["1319216400", "32"], ["1319220000", "46"], ["1319223600", "88"], ["1319227200", "89"], ["1319230800", "76"], ["1319234400", "66"], ["1319238000", "64"]], "extStartTime": 1319148000, "measType": "auto", "interval": 3600, "thresholdsForAvg": {"min": null, "avg": null, "max": null}, "scaleMin": null, "coverageRate": 0.75, "paramPostfix": "", "count": 24, "unitLabel": "&micro;g/m<sup>3</sup>", "startTime": 1319155200}, {"chartTooltipContent": "%y.# %ly o godz. %x", "paramLabel": "Tlenek azotu", "label": "Tlenek azotu", "aggType": "A1h", "decimals": 0, "avg": {"min": "10", "avg": 79.217391304348, "max": "215"}, "retroCount": 2, "scaleMax": null, "paramId": "no", "unit": "ug/m3", "paramCode": "NO", "thresholds": null, "ord": 14, "isAvgValid": true, "data": [["1319148000", "37"], ["1319151600", "31"], ["1319155200", "43"], ["1319158800", "40"], ["1319162400", "34"], ["1319166000", "27"], ["1319169600", "53"], ["1319173200", "121"], ["1319176800", "139"], ["1319180400", "163"], ["1319184000", "160"], ["1319187600", "35"], ["1319191200", "17"], ["1319194800", "13"], ["1319198400", "10"], ["1319202000", "13"], ["1319205600", "14"], ["1319209200", "24"], ["1319212800", "46"], ["1319216400", "123"], ["1319220000", "214"], ["1319227200", "215"], ["1319230800", "126"], ["1319234400", "111"], ["1319238000", "81"]], "extStartTime": 1319148000, "measType": "auto", "interval": 3600, "thresholdsForAvg": {"min": null, "avg": null, "max": null}, "scaleMin": null, "coverageRate": 0.75, "paramPostfix": "", "count": 24, "unitLabel": "&micro;g/m<sup>3</sup>", "startTime": 1319155200}, {"chartTooltipContent": "%y.# %ly o godz. %x", "paramLabel": "Tlenki azotu", "label": "Tlenki azotu", "aggType": "A1h", "decimals": 0, "avg": {"min": "39", "avg": 154.65217391304, "max": "388"}, "retroCount": 2, "scaleMax": null, "paramId": "nox", "unit": "ug/m3", "paramCode": "NO<sub>x</sub>", "thresholds": null, "ord": 3, "isAvgValid": true, "data": [["1319148000", "86"], ["1319151600", "76"], ["1319155200", "90"], ["1319158800", "84"], ["1319162400", "71"], ["1319166000", "61"], ["1319169600", "102"], ["1319173200", "208"], ["1319176800", "239"], ["1319180400", "283"], ["1319184000", "286"], ["1319187600", "85"], ["1319191200", "49"], ["1319194800", "45"], ["1319198400", "39"], ["1319202000", "49"], ["1319205600", "58"], ["1319209200", "84"], ["1319212800", "127"], ["1319216400", "252"], ["1319220000", "388"], ["1319227200", "377"], ["1319230800", "230"], ["1319234400", "201"], ["1319238000", "149"]], "extStartTime": 1319148000, "measType": "auto", "interval": 3600, "thresholdsForAvg": {"min": null, "avg": null, "max": null}, "scaleMin": null, "coverageRate": 0.75, "paramPostfix": "", "count": 24, "unitLabel": "&micro;g/m<sup>3</sup>", "startTime": 1319155200}], "charts": [], "viewType": "station", "title": "Dane pomiarowe dla stacji Krak\u00f3w-Kurdwan\u00f3w w dniu 21.10.2011 r.", "dateFormat": "H:00", "unitLabel": "&micro;g/m<sup>3</sup>"}, "success": true}