{"data": {"series": [{"chartTooltipContent": "%y.# %ly o godz. %x", "paramLabel": "Dwutlenek azotu", "label": "Dwutlenek azotu", "aggType": "A1h", "decimals": 0, "avg": {"min": "12", "avg": 22.958333333333, "max": "45"}, "retroCount": 2, "scaleMax": null, "paramId": "no2", "unit": "ug/m3", "paramCode": "NO<sub>2</sub>", "thresholds": {"atDecimals": 0, "at": 400, "tv": null, "it": null, "itDecimals": 0, "lv": 200, "lvDecimals": 0, "tvDecimals": 0}, "ord": 2, "isAvgValid": true, "data": [["1298844000", "20"], ["1298847600", "18"], ["1298851200", "16"], ["1298854800", "14"], ["1298858400", "13"], ["1298862000", "13"], ["1298865600", "12"], ["1298869200", "16"], ["1298872800", "19"], ["1298876400", "21"], ["1298880000", "22"], ["1298883600", "18"], ["1298887200", "17"], ["1298890800", "19"], ["1298894400", "22"], ["1298898000", "18"], ["1298901600", "19"], ["1298905200", "20"], ["1298908800", "20"], ["1298912400", "25"], ["1298916000", "36"], ["1298919600", "45"], ["1298923200", "39"], ["1298926800", "32"], ["1298930400", "39"], ["1298934000", "36"]], "extStartTime": 1298844000, "measType": "auto", "interval": 3600, "thresholdsForAvg": {"min": null, "avg": null, "max": null}, "scaleMin": null, "coverageRate": 0.75, "paramPostfix": "", "count": 24, "unitLabel": "&micro;g/m<sup>3</sup>", "startTime": 1298851200}, {"chartTooltipContent": "%y.# %ly o godz. %x", "paramLabel": "Dwutlenek siarki", "label": "Dwutlenek siarki<sup>3)</sup>", "aggType": "A1h", "decimals": 1, "avg": {"min": "8", "avg": 13.173913043478, "max": "25"}, "retroCount": 2, "scaleMax": null, "paramId": "so2", "unit": "ug/m3", "paramCode": "SO<sub>2</sub>", "thresholds": {"atDecimals": 0, "at": 500, "tv": null, "it": null, "itDecimals": 0, "lv": 350, "lvDecimals": 0, "tvDecimals": 0}, "ord": 1, "isAvgValid": true, "data": [["1298844000", "8"], ["1298847600", "9"], ["1298851200", "11"], ["1298854800", "11"], ["1298858400", "11"], ["1298862000", "9"], ["1298865600", "8"], ["1298869200", "8"], ["1298872800", "8"], ["1298876400", "12"], ["1298880000", "22"], ["1298883600", "23"], ["1298887200", "20"], ["1298890800", "25"], ["1298894400", "19"], ["1298901600", "12"], ["1298905200", "12"], ["1298908800", "11"], ["1298912400", "11"], ["1298916000", "15"], ["1298919600", "14"], ["1298923200", "12"], ["1298926800", "9"], ["1298930400", "10"], ["1298934000", "10"]], "extStartTime": 1298844000, "measType": "auto", "interval": 3600, "thresholdsForAvg": {"min": null, "avg": {"atDecimals": 0, "at": null, "tv": null, "it": null, "itDecimals": 0, "lv": 125, "lvDecimals": 0, "tvDecimals": 0}, "max": null}, "scaleMin": null, "coverageRate": 0.75, "paramPostfix": "<sup>3)</sup>", "count": 24, "unitLabel": "&micro;g/m<sup>3</sup>", "startTime": 1298851200}, {"chartTooltipContent": "%y.# %ly o godz. %x", "paramLabel": "Ozon", "label": "Ozon", "aggType": "A1h", "decimals": 0, "avg": {"min": "42", "avg": 65.083333333333, "max": "84"}, "retroCount": 2, "scaleMax": null, "paramId": "o3", "unit": "ug/m3", "paramCode": "O<sub>3</sub>", "thresholds": {"atDecimals": 0, "at": 240, "tv": null, "it": 180, "itDecimals": 0, "lv": null, "lvDecimals": 0, "tvDecimals": 0}, "ord": 4, "isAvgValid": true, "data": [["1298844000", "67"], ["1298847600", "67"], ["1298851200", "68"], ["1298854800", "67"], ["1298858400", "67"], ["1298862000", "69"], ["1298865600", "70"], ["1298869200", "65"], ["1298872800", "64"], ["1298876400", "64"], ["1298880000", "64"], ["1298883600", "68"], ["1298887200", "70"], ["1298890800", "69"], ["1298894400", "72"], ["1298898000", "81"], ["1298901600", "83"], ["1298905200", "84"], ["1298908800", "79"], ["1298912400", "70"], ["1298916000", "55"], ["1298919600", "47"], ["1298923200", "50"], ["1298926800", "51"], ["1298930400", "42"], ["1298934000", "43"]], "extStartTime": 1298844000, "measType": "auto", "interval": 3600, "thresholdsForAvg": {"min": null, "avg": null, "max": null}, "scaleMin": null, "coverageRate": 0.75, "paramPostfix": "", "count": 24, "unitLabel": "&micro;g/m<sup>3</sup>", "startTime": 1298851200}, {"chartTooltipContent": "%y.# %ly o godz. %x", "paramLabel": "Ozon", "label": "Ozon 8h<sup>2)</sup>", "aggType": "sA8h", "decimals": 0, "avg": {"min": null, "avg": null, "max": null}, "retroCount": 2, "scaleMax": null, "paramId": "o3", "unit": "ug/m3", "paramCode": "O<sub>3</sub>", "thresholds": {"atDecimals": 0, "at": null, "tv": 120, "it": null, "itDecimals": 0, "lv": null, "lvDecimals": 0, "tvDecimals": 0}, "ord": 4, "isAvgValid": false, "data": [], "extStartTime": 1298844000, "measType": "auto", "interval": 3600, "thresholdsForAvg": {"min": null, "avg": null, "max": {"atDecimals": 0, "at": null, "tv": 120, "it": null, "itDecimals": 0, "lv": null, "lvDecimals": 0, "tvDecimals": 0}}, "scaleMin": null, "coverageRate": 0.75, "paramPostfix": " 8h<sup>2)</sup>", "count": 24, "unitLabel": "&micro;g/m<sup>3</sup>", "startTime": 1298851200}, {"chartTooltipContent": "%y.# %ly o godz. %x", "paramLabel": "Py\u0142 zawieszony PM10", "label": "Py\u0142 zawieszony PM10", "aggType": "A1h", "decimals": 0, "avg": {"min": "44", "avg": 60.541666666667, "max": "90"}, "retroCount": 2, "scaleMax": null, "paramId": "pm10", "unit": "ug/m3", "paramCode": "PM10", "thresholds": {"atDecimals": 0, "at": null, "tv": null, "it": null, "itDecimals": 0, "lv": null, "lvDecimals": 0, "tvDecimals": 0}, "ord": 7, "isAvgValid": true, "data": [["1298844000", "57"], ["1298847600", "56"], ["1298851200", "54"], ["1298854800", "52"], ["1298858400", "45"], ["1298862000", "45"], ["1298865600", "45"], ["1298869200", "44"], ["1298872800", "51"], ["1298876400", "55"], ["1298880000", "58"], ["1298883600", "59"], ["1298887200", "64"], ["1298890800", "63"], ["1298894400", "68"], ["1298898000", "53"], ["1298901600", "54"], ["1298905200", "63"], ["1298908800", "49"], ["1298912400", "52"], ["1298916000", "64"], ["1298919600", "78"], ["1298923200", "82"], ["1298926800", "81"], ["1298930400", "90"], ["1298934000", "84"]], "extStartTime": 1298844000, "measType": "auto", "interval": 3600, "thresholdsForAvg": {"min": null, "avg": {"atDecimals": 0, "at": 300, "tv": null, "it": 200, "itDecimals": 0, "lv": 50, "lvDecimals": 0, "tvDecimals": 0}, "max": null}, "scaleMin": null, "coverageRate": 0.75, "paramPostfix": "", "count": 24, "unitLabel": "&micro;g/m<sup>3</sup>", "startTime": 1298851200}, {"chartTooltipContent": "%y.# %ly o godz. %x", "paramLabel": "Py\u0142 zawieszony PM2.5", "label": "Py\u0142 zawieszony PM2.5", "aggType": "A1h", "decimals": 0, "avg": {"min": "26", "avg": 39.25, "max": "70"}, "retroCount": 2, "scaleMax": null, "paramId": "pm2.5", "unit": "ug/m3", "paramCode": "PM2.5", "thresholds": {"atDecimals": 0, "at": null, "tv": null, "it": null, "itDecimals": 0, "lv": null, "lvDecimals": 0, "tvDecimals": 0}, "ord": 8, "isAvgValid": true, "data": [["1298844000", "38"], ["1298847600", "39"], ["1298851200", "38"], ["1298854800", "34"], ["1298858400", "30"], ["1298862000", "30"], ["1298865600", "26"], ["1298869200", "28"], ["1298872800", "32"], ["1298876400", "30"], ["1298880000", "34"], ["1298883600", "34"], ["1298887200", "38"], ["1298890800", "40"], ["1298894400", "39"], ["1298898000", "35"], ["1298901600", "36"], ["1298905200", "28"], ["1298908800", "27"], ["1298912400", "31"], ["1298916000", "44"], ["1298919600", "57"], ["1298923200", "54"], ["1298926800", "62"], ["1298930400", "70"], ["1298934000", "65"]], "extStartTime": 1298844000, "measType": "auto", "interval": 3600, "thresholdsForAvg": {"min": null, "avg": null, "max": null}, "scaleMin": null, "coverageRate": 0.75, "paramPostfix": "", "count": 24, "unitLabel": "&micro;g/m<sup>3</sup>", "startTime": 1298851200}, {"chartTooltipContent": "%y.# %ly o godz. %x", "paramLabel": "Tlenek azotu", "label": "Tlenek azotu", "aggType": "A1h", "decimals": 0, "avg": {"min": "0", "avg": 1.2083333333333, "max": "3"}, "retroCount": 2, "scaleMax": null, "paramId": "no", "unit": "ug/m3", "paramCode": "NO", "thresholds": null, "ord": 14, "isAvgValid": true, "data": [["1298844000", "1"], ["1298847600", "1"], ["1298851200", "0"], ["1298854800", "0"], ["1298858400", "0"], ["1298862000", "0"], ["1298865600", "0"], ["1298869200", "0"], ["1298872800", "1"], ["1298876400", "2"], ["1298880000", "3"], ["1298883600", "2"], ["1298887200", "2"], ["1298890800", "3"], ["1298894400", "3"], ["1298898000", "1"], ["1298901600", "1"], ["1298905200", "1"], ["1298908800", "0"], ["1298912400", "1"], ["1298916000", "1"], ["1298919600", "2"], ["1298923200", "1"], ["1298926800", "1"], ["1298930400", "2"], ["1298934000", "2"]], "extStartTime": 1298844000, "measType": "auto", "interval": 3600, "thresholdsForAvg": {"min": null, "avg": null, "max": null}, "scaleMin": null, "coverageRate": 0.75, "paramPostfix": "", "count": 24, "unitLabel": "&micro;g/m<sup>3</sup>", "startTime": 1298851200}, {"chartTooltipContent": "%y.# %ly o godz. %x", "paramLabel": "Tlenki azotu", "label": "Tlenki azotu", "aggType": "A1h", "decimals": 0, "avg": {"min": "13", "avg": 25.166666666667, "max": "47"}, "retroCount": 2, "scaleMax": null, "paramId": "nox", "unit": "ug/m3", "paramCode": "NO<sub>x</sub>", "thresholds": null, "ord": 3, "isAvgValid": true, "data": [["1298844000", "21"], ["1298847600", "20"], ["1298851200", "17"], ["1298854800", "15"], ["1298858400", "14"], ["1298862000", "13"], ["1298865600", "13"], ["1298869200", "17"], ["1298872800", "21"], ["1298876400", "23"], ["1298880000", "26"], ["1298883600", "21"], ["1298887200", "20"], ["1298890800", "24"], ["1298894400", "26"], ["1298898000", "21"], ["1298901600", "22"], ["1298905200", "22"], ["1298908800", "21"], ["1298912400", "26"], ["1298916000", "38"], ["1298919600", "47"], ["1298923200", "41"], ["1298926800", "35"], ["1298930400", "42"], ["1298934000", "39"]], "extStartTime": 1298844000, "measType": "auto", "interval": 3600, "thresholdsForAvg": {"min": null, "avg": null, "max": null}, "scaleMin": null, "coverageRate": 0.75, "paramPostfix": "", "count": 24, "unitLabel": "&micro;g/m<sup>3</sup>", "startTime": 1298851200}], "charts": [], "viewType": "station", "title": "Dane pomiarowe dla stacji Krak\u00f3w-Kurdwan\u00f3w w dniu 28.02.2011 r.", "dateFormat": "H:00", "unitLabel": "&micro;g/m<sup>3</sup>"}, "success": true}