{"data": {"series": [{"chartTooltipContent": "%y.# %ly o godz. %x", "paramLabel": "Benzen", "label": "Benzen", "aggType": "A1h", "decimals": 1, "avg": {"min": "0.6", "avg": 3.6875, "max": "9.5"}, "retroCount": 2, "scaleMax": null, "paramId": "bzn", "unit": "ug/m3", "paramCode": "C<sub>6</sub>H<sub>6</sub>", "thresholds": {"atDecimals": 0, "at": null, "tv": null, "it": null, "itDecimals": 0, "lv": null, "lvDecimals": 0, "tvDecimals": 0}, "ord": 6, "isAvgValid": true, "data": [["1189980000", "5.6"], ["1189983600", "3.7"], ["1189987200", "3"], ["1189990800", "3"], ["1189994400", "3"], ["1189998000", "2.6"], ["1190001600", "2.9"], ["1190005200", "2.6"], ["1190008800", "2.4"], ["1190012400", "3.4"], ["1190016000", "4.4"], ["1190019600", "8"], ["1190023200", "6.2"], ["1190026800", "1.9"], ["1190030400", "1"], ["1190034000", "1"], ["1190037600", "0.8"], ["1190041200", "0.6"], ["1190044800", "0.7"], ["1190048400", "1.9"], ["1190052000", "2.4"], ["1190055600", "5.4"], ["1190059200", "6.6"], ["1190062800", "7.8"], ["1190066400", "9.5"], ["1190070000", "7.4"]], "extStartTime": 1189980000, "measType": "auto", "interval": 3600, "thresholdsForAvg": {"min": null, "avg": null, "max": null}, "scaleMin": null, "coverageRate": 0.75, "paramPostfix": "", "count": 24, "unitLabel": "&micro;g/m<sup>3</sup>", "startTime": 1189987200}, {"chartTooltipContent": "%y.# %ly o godz. %x", "paramLabel": "Dwutlenek azotu", "label": "Dwutlenek azotu", "aggType": "A1h", "decimals": 0, "avg": {"min": "9", "avg": 31.791666666667, "max": "63"}, "retroCount": 2, "scaleMax": null, "paramId": "no2", "unit": "ug/m3", "paramCode": "NO<sub>2</sub>", "thresholds": {"atDecimals": 0, "at": 400, "tv": null, "it": null, "itDecimals": 0, "lv": 200, "lvDecimals": 0, "tvDecimals": 0}, "ord": 2, "isAvgValid": true, "data": [["1189980000", "22"], ["1189983600", "17"], ["1189987200", "14"], ["1189990800", "12"], ["1189994400", "11"], ["1189998000", "9"], ["1190001600", "10"], ["1190005200", "11"], ["1190008800", "17"], ["1190012400", "39"], ["1190016000", "45"], ["1190019600", "43"], ["1190023200", "51"], ["1190026800", "22"], ["1190030400", "21"], ["1190034000", "27"], ["1190037600", "27"], ["1190041200", "38"], ["1190044800", "62"], ["1190048400", "55"], ["1190052000", "52"], ["1190055600", "63"], ["1190059200", "50"], ["1190062800", "36"], ["1190066400", "28"], ["1190070000", "20"]], "extStartTime": 1189980000, "measType": "auto", "interval": 3600, "thresholdsForAvg": {"min": null, "avg": null, "max": null}, "scaleMin": null, "coverageRate": 0.75, "paramPostfix": "", "count": 24, "unitLabel": "&micro;g/m<sup>3</sup>", "startTime": 1189987200}, {"chartTooltipContent": "%y.# %ly o godz. %x", "paramLabel": "Dwutlenek siarki", "label": "Dwutlenek siarki<sup>3)</sup>", "aggType": "A1h", "decimals": 1, "avg": {"min": "5", "avg": 12.181818181818, "max": "34"}, "retroCount": 2, "scaleMax": null, "paramId": "so2", "unit": "ug/m3", "paramCode": "SO<sub>2</sub>", "thresholds": {"atDecimals": 0, "at": 500, "tv": null, "it": null, "itDecimals": 0, "lv": 350, "lvDecimals": 0, "tvDecimals": 0}, "ord": 1, "isAvgValid": true, "data": [["1189980000", "9"], ["1189983600", "9"], ["1189987200", "8"], ["1189990800", "7"], ["1189994400", "7"], ["1189998000", "7"], ["1190001600", "7"], ["1190005200", "8"], ["1190008800", "8"], ["1190012400", "9"], ["1190016000", "9"], ["1190019600", "9"], ["1190030400", "14"], ["1190034000", "19"], ["1190037600", "17"], ["1190041200", "31"], ["1190044800", "34"], ["1190048400", "17"], ["1190052000", "12"], ["1190055600", "12"], ["1190059200", "11"], ["1190062800", "10"], ["1190066400", "7"], ["1190070000", "5"]], "extStartTime": 1189980000, "measType": "auto", "interval": 3600, "thresholdsForAvg": {"min": null, "avg": {"atDecimals": 0, "at": null, "tv": null, "it": null, "itDecimals": 0, "lv": 125, "lvDecimals": 0, "tvDecimals": 0}, "max": null}, "scaleMin": null, "coverageRate": 0.75, "paramPostfix": "<sup>3)</sup>", "count": 24, "unitLabel": "&micro;g/m<sup>3</sup>", "startTime": 1189987200}, {"chartTooltipContent": "%y.# %ly o godz. %x", "paramLabel": "Py\u0142 zawieszony PM10", "label": "Py\u0142 zawieszony PM10", "aggType": "A1h", "decimals": 0, "avg": {"min": "41", "avg": 57.708333333333, "max": "99"}, "retroCount": 2, "scaleMax": null, "paramId": "pm10", "unit": "ug/m3", "paramCode": "PM10", "thresholds": {"atDecimals": 0, "at": null, "tv": null, "it": null, "itDecimals": 0, "lv": null, "lvDecimals": 0, "tvDecimals": 0}, "ord": 7, "isAvgValid": true, "data": [["1189980000", "44"], ["1189983600", "44"], ["1189987200", "52"], ["1189990800", "52"], ["1189994400", "52"], ["1189998000", "44"], ["1190001600", "44"], ["1190005200", "44"], ["1190008800", "41"], ["1190012400", "41"], ["1190016000", "41"], ["1190019600", "73"], ["1190023200", "73"], ["1190026800", "73"], ["1190030400", "65"], ["1190034000", "65"], ["1190037600", "65"], ["1190041200", "42"], ["1190044800", "42"], ["1190048400", "42"], ["1190052000", "46"], ["1190055600", "46"], ["1190059200", "46"], ["1190062800", "98"], ["1190066400", "99"], ["1190070000", "99"]], "extStartTime": 1189980000, "measType": "auto", "interval": 3600, "thresholdsForAvg": {"min": null, "avg": {"atDecimals": 0, "at": 300, "tv": null, "it": 200, "itDecimals": 0, "lv": 50, "lvDecimals": 0, "tvDecimals": 0}, "max": null}, "scaleMin": null, "coverageRate": 0.75, "paramPostfix": "", "count": 24, "unitLabel": "&micro;g/m<sup>3</sup>", "startTime": 1189987200}, {"chartTooltipContent": "%y.# %ly o godz. %x", "paramLabel": "Py\u0142 zawieszony PM2.5", "label": "Py\u0142 zawieszony PM2.5", "aggType": "A1h", "decimals": 0, "avg": {"min": null, "avg": null, "max": null}, "retroCount": 2, "scaleMax": null, "paramId": "pm2.5", "unit": "ug/m3", "paramCode": "PM2.5", "thresholds": {"atDecimals": 0, "at": null, "tv": null, "it": null, "itDecimals": 0, "lv": null, "lvDecimals": 0, "tvDecimals": 0}, "ord": 8, "isAvgValid": false, "data": [], "extStartTime": 1189980000, "measType": "auto", "interval": 3600, "thresholdsForAvg": {"min": null, "avg": null, "max": null}, "scaleMin": null, "coverageRate": 0.75, "paramPostfix": "", "count": 24, "unitLabel": "&micro;g/m<sup>3</sup>", "startTime": 1189987200}, {"chartTooltipContent": "%y.# %ly o godz. %x", "paramLabel": "Tlenek azotu", "label": "Tlenek azotu", "aggType": "A1h", "decimals": 0, "avg": {"min": "9", "avg": 68.708333333333, "max": "180"}, "retroCount": 2, "scaleMax": null, "paramId": "no", "unit": "ug/m3", "paramCode": "NO", "thresholds": null, "ord": 14, "isAvgValid": true, "data": [["1189980000", "67"], ["1189983600", "39"], ["1189987200", "43"], ["1189990800", "42"], ["1189994400", "34"], ["1189998000", "25"], ["1190001600", "44"], ["1190005200", "64"], ["1190008800", "115"], ["1190012400", "126"], ["1190016000", "94"], ["1190019600", "51"], ["1190023200", "29"], ["1190026800", "9"], ["1190030400", "9"], ["1190034000", "10"], ["1190037600", "13"], ["1190041200", "14"], ["1190044800", "25"], ["1190048400", "50"], ["1190052000", "90"], ["1190055600", "149"], ["1190059200", "176"], ["1190062800", "180"], ["1190066400", "153"], ["1190070000", "104"]], "extStartTime": 1189980000, "measType": "auto", "interval": 3600, "thresholdsForAvg": {"min": null, "avg": null, "max": null}, "scaleMin": null, "coverageRate": 0.75, "paramPostfix": "", "count": 24, "unitLabel": "&micro;g/m<sup>3</sup>", "startTime": 1189987200}, {"chartTooltipContent": "%y.# %ly o godz. %x", "paramLabel": "Tlenek w\u0119gla", "label": "Tlenek w\u0119gla", "aggType": "A1h", "decimals": 0, "avg": {"min": 460, "avg": 1075.652173913, "max": 2330}, "retroCount": 2, "scaleMax": null, "paramId": "co", "unit": "ug/m3", "paramCode": "CO", "thresholds": {"atDecimals": 0, "at": null, "tv": null, "it": null, "itDecimals": 0, "lv": null, "lvDecimals": 0, "tvDecimals": 0}, "ord": 5, "isAvgValid": true, "data": [["1189980000", 1060], ["1189987200", 910], ["1189990800", 900], ["1189994400", 830], ["1189998000", 770], ["1190001600", 820], ["1190005200", 910], ["1190008800", 1180], ["1190012400", 1330], ["1190016000", 1350], ["1190019600", 880], ["1190023200", 710], ["1190026800", 460], ["1190030400", 460], ["1190034000", 510], ["1190037600", 510], ["1190041200", 590], ["1190044800", 880], ["1190048400", 1020], ["1190052000", 1590], ["1190055600", 1900], ["1190059200", 2250], ["1190062800", 2330], ["1190070000", 1650]], "extStartTime": 1189980000, "measType": "auto", "interval": 3600, "thresholdsForAvg": {"min": null, "avg": {"atDecimals": 0, "at": null, "tv": null, "it": null, "itDecimals": 0, "lv": null, "lvDecimals": 0, "tvDecimals": 0}, "max": null}, "scaleMin": null, "coverageRate": 0.75, "paramPostfix": "", "count": 24, "unitLabel": "&micro;g/m<sup>3</sup>", "startTime": 1189987200}, {"chartTooltipContent": "%y.# %ly o godz. %x", "paramLabel": "Tlenek w\u0119gla", "label": "Tlenek w\u0119gla 8h<sup>2)</sup>", "aggType": "sA8h", "decimals": 0, "avg": {"min": null, "avg": null, "max": null}, "retroCount": 2, "scaleMax": null, "paramId": "co", "unit": "ug/m3", "paramCode": "CO", "thresholds": {"atDecimals": 0, "at": null, "tv": null, "it": null, "itDecimals": 0, "lv": 10000, "lvDecimals": 0, "tvDecimals": 0}, "ord": 5, "isAvgValid": false, "data": [], "extStartTime": 1189980000, "measType": "auto", "interval": 3600, "thresholdsForAvg": {"min": null, "avg": null, "max": {"atDecimals": 0, "at": null, "tv": null, "it": null, "itDecimals": 0, "lv": 10000, "lvDecimals": 0, "tvDecimals": 0}}, "scaleMin": null, "coverageRate": 0.75, "paramPostfix": " 8h<sup>2)</sup>", "count": 24, "unitLabel": "&micro;g/m<sup>3</sup>", "startTime": 1189987200}, {"chartTooltipContent": "%y.# %ly o godz. %x", "paramLabel": "Tlenki azotu", "label": "Tlenki azotu", "aggType": "A1h", "decimals": 0, "avg": {"min": "36", "avg": 137.25, "max": "320"}, "retroCount": 2, "scaleMax": null, "paramId": "nox", "unit": "ug/m3", "paramCode": "NO<sub>x</sub>", "thresholds": null, "ord": 3, "isAvgValid": true, "data": [["1189980000", "125"], ["1189983600", "76"], ["1189987200", "80"], ["1189990800", "77"], ["1189994400", "64"], ["1189998000", "48"], ["1190001600", "78"], ["1190005200", "109"], ["1190008800", "192"], ["1190012400", "232"], ["1190016000", "188"], ["1190019600", "121"], ["1190023200", "96"], ["1190026800", "36"], ["1190030400", "36"], ["1190034000", "43"], ["1190037600", "48"], ["1190041200", "59"], ["1190044800", "101"], ["1190048400", "132"], ["1190052000", "190"], ["1190055600", "291"], ["1190059200", "320"], ["1190062800", "312"], ["1190066400", "262"], ["1190070000", "179"]], "extStartTime": 1189980000, "measType": "auto", "interval": 3600, "thresholdsForAvg": {"min": null, "avg": null, "max": null}, "scaleMin": null, "coverageRate": 0.75, "paramPostfix": "", "count": 24, "unitLabel": "&micro;g/m<sup>3</sup>", "startTime": 1189987200}], "charts": [], "viewType": "station", "title": "Dane pomiarowe dla stacji Nowa Huta w dniu 17.09.2007 r.", "dateFormat": "H:00", "unitLabel": "&micro;g/m<sup>3</sup>"}, "success": true}