{"data": {"series": [{"chartTooltipContent": "%y.# %ly o godz. %x", "paramLabel": "Benzen", "label": "Benzen", "aggType": "A1h", "decimals": 1, "avg": {"min": null, "avg": null, "max": null}, "retroCount": 2, "scaleMax": null, "paramId": "bzn", "unit": "ug/m3", "paramCode": "C<sub>6</sub>H<sub>6</sub>", "thresholds": {"atDecimals": 0, "at": null, "tv": null, "it": null, "itDecimals": 0, "lv": null, "lvDecimals": 0, "tvDecimals": 0}, "ord": 6, "isAvgValid": false, "data": [], "extStartTime": 1311717600, "measType": "auto", "interval": 3600, "thresholdsForAvg": {"min": null, "avg": null, "max": null}, "scaleMin": null, "coverageRate": 0.75, "paramPostfix": "", "count": 24, "unitLabel": "&micro;g/m<sup>3</sup>", "startTime": 1311724800}, {"chartTooltipContent": "%y.# %ly o godz. %x", "paramLabel": "Dwutlenek azotu", "label": "Dwutlenek azotu", "aggType": "A1h", "decimals": 0, "avg": {"min": "22", "avg": 40.375, "max": "63"}, "retroCount": 2, "scaleMax": null, "paramId": "no2", "unit": "ug/m3", "paramCode": "NO<sub>2</sub>", "thresholds": {"atDecimals": 0, "at": 400, "tv": null, "it": null, "itDecimals": 0, "lv": 200, "lvDecimals": 0, "tvDecimals": 0}, "ord": 2, "isAvgValid": true, "data": [["1311717600", "38"], ["1311721200", "26"], ["1311724800", "33"], ["1311728400", "32"], ["1311732000", "22"], ["1311735600", "26"], ["1311739200", "28"], ["1311742800", "31"], ["1311746400", "40"], ["1311750000", "37"], ["1311753600", "35"], ["1311757200", "34"], ["1311760800", "39"], ["1311764400", "34"], ["1311768000", "45"], ["1311771600", "44"], ["1311775200", "43"], ["1311778800", "58"], ["1311782400", "59"], ["1311786000", "63"], ["1311789600", "60"], ["1311793200", "47"], ["1311796800", "44"], ["1311800400", "48"], ["1311804000", "38"], ["1311807600", "29"]], "extStartTime": 1311717600, "measType": "auto", "interval": 3600, "thresholdsForAvg": {"min": null, "avg": null, "max": null}, "scaleMin": null, "coverageRate": 0.75, "paramPostfix": "", "count": 24, "unitLabel": "&micro;g/m<sup>3</sup>", "startTime": 1311724800}, {"chartTooltipContent": "%y.# %ly o godz. %x", "paramLabel": "Dwutlenek siarki", "label": "Dwutlenek siarki<sup>3)</sup>", "aggType": "A1h", "decimals": 1, "avg": {"min": "1", "avg": 3.5, "max": "9"}, "retroCount": 2, "scaleMax": null, "paramId": "so2", "unit": "ug/m3", "paramCode": "SO<sub>2</sub>", "thresholds": {"atDecimals": 0, "at": 500, "tv": null, "it": null, "itDecimals": 0, "lv": 350, "lvDecimals": 0, "tvDecimals": 0}, "ord": 1, "isAvgValid": true, "data": [["1311717600", "2"], ["1311721200", "2"], ["1311724800", "2"], ["1311728400", "2"], ["1311732000", "1"], ["1311735600", "3"], ["1311739200", "3"], ["1311742800", "3"], ["1311746400", "3"], ["1311750000", "3"], ["1311753600", "4"], ["1311757200", "7"], ["1311760800", "8"], ["1311764400", "8"], ["1311768000", "9"], ["1311771600", "6"], ["1311775200", "3"], ["1311778800", "4"], ["1311782400", "3"], ["1311786000", "2"], ["1311789600", "2"], ["1311793200", "2"], ["1311796800", "2"], ["1311800400", "2"], ["1311804000", "1"], ["1311807600", "1"]], "extStartTime": 1311717600, "measType": "auto", "interval": 3600, "thresholdsForAvg": {"min": null, "avg": {"atDecimals": 0, "at": null, "tv": null, "it": null, "itDecimals": 0, "lv": 125, "lvDecimals": 0, "tvDecimals": 0}, "max": null}, "scaleMin": null, "coverageRate": 0.75, "paramPostfix": "<sup>3)</sup>", "count": 24, "unitLabel": "&micro;g/m<sup>3</sup>", "startTime": 1311724800}, {"chartTooltipContent": "%y.# %ly o godz. %x", "paramLabel": "Py\u0142 zawieszony PM10", "label": "Py\u0142 zawieszony PM10", "aggType": "A1h", "decimals": 0, "avg": {"min": "21", "avg": 42.416666666667, "max": "66"}, "retroCount": 2, "scaleMax": null, "paramId": "pm10", "unit": "ug/m3", "paramCode": "PM10", "thresholds": {"atDecimals": 0, "at": null, "tv": null, "it": null, "itDecimals": 0, "lv": null, "lvDecimals": 0, "tvDecimals": 0}, "ord": 7, "isAvgValid": true, "data": [["1311717600", "41"], ["1311721200", "29"], ["1311724800", "34"], ["1311728400", "46"], ["1311732000", "54"], ["1311735600", "62"], ["1311739200", "66"], ["1311742800", "62"], ["1311746400", "62"], ["1311750000", "59"], ["1311753600", "52"], ["1311757200", "46"], ["1311760800", "44"], ["1311764400", "46"], ["1311768000", "45"], ["1311771600", "36"], ["1311775200", "27"], ["1311778800", "29"], ["1311782400", "30"], ["1311786000", "27"], ["1311789600", "22"], ["1311793200", "21"], ["1311796800", "29"], ["1311800400", "36"], ["1311804000", "44"], ["1311807600", "39"]], "extStartTime": 1311717600, "measType": "auto", "interval": 3600, "thresholdsForAvg": {"min": null, "avg": {"atDecimals": 0, "at": 300, "tv": null, "it": 200, "itDecimals": 0, "lv": 50, "lvDecimals": 0, "tvDecimals": 0}, "max": null}, "scaleMin": null, "coverageRate": 0.75, "paramPostfix": "", "count": 24, "unitLabel": "&micro;g/m<sup>3</sup>", "startTime": 1311724800}, {"chartTooltipContent": "%y.# %ly o godz. %x", "paramLabel": "Py\u0142 zawieszony PM2.5", "label": "Py\u0142 zawieszony PM2.5", "aggType": "A1h", "decimals": 0, "avg": {"min": "12", "avg": 25.458333333333, "max": "41"}, "retroCount": 2, "scaleMax": null, "paramId": "pm2.5", "unit": "ug/m3", "paramCode": "PM2.5", "thresholds": {"atDecimals": 0, "at": null, "tv": null, "it": null, "itDecimals": 0, "lv": null, "lvDecimals": 0, "tvDecimals": 0}, "ord": 8, "isAvgValid": true, "data": [["1311717600", "22"], ["1311721200", "15"], ["1311724800", "19"], ["1311728400", "28"], ["1311732000", "34"], ["1311735600", "39"], ["1311739200", "41"], ["1311742800", "39"], ["1311746400", "38"], ["1311750000", "35"], ["1311753600", "33"], ["1311757200", "30"], ["1311760800", "27"], ["1311764400", "25"], ["1311768000", "25"], ["1311771600", "21"], ["1311775200", "17"], ["1311778800", "18"], ["1311782400", "18"], ["1311786000", "17"], ["1311789600", "13"], ["1311793200", "12"], ["1311796800", "15"], ["1311800400", "21"], ["1311804000", "24"], ["1311807600", "22"]], "extStartTime": 1311717600, "measType": "auto", "interval": 3600, "thresholdsForAvg": {"min": null, "avg": null, "max": null}, "scaleMin": null, "coverageRate": 0.75, "paramPostfix": "", "count": 24, "unitLabel": "&micro;g/m<sup>3</sup>", "startTime": 1311724800}, {"chartTooltipContent": "%y.# %ly o godz. %x", "paramLabel": "Tlenek azotu", "label": "Tlenek azotu", "aggType": "A1h", "decimals": 0, "avg": {"min": "2", "avg": 20.041666666667, "max": "44"}, "retroCount": 2, "scaleMax": null, "paramId": "no", "unit": "ug/m3", "paramCode": "NO", "thresholds": null, "ord": 14, "isAvgValid": true, "data": [["1311717600", "20"], ["1311721200", "4"], ["1311724800", "4"], ["1311728400", "5"], ["1311732000", "2"], ["1311735600", "4"], ["1311739200", "10"], ["1311742800", "14"], ["1311746400", "30"], ["1311750000", "29"], ["1311753600", "22"], ["1311757200", "18"], ["1311760800", "16"], ["1311764400", "12"], ["1311768000", "21"], ["1311771600", "18"], ["1311775200", "16"], ["1311778800", "22"], ["1311782400", "27"], ["1311786000", "26"], ["1311789600", "25"], ["1311793200", "17"], ["1311796800", "35"], ["1311800400", "44"], ["1311804000", "27"], ["1311807600", "37"]], "extStartTime": 1311717600, "measType": "auto", "interval": 3600, "thresholdsForAvg": {"min": null, "avg": null, "max": null}, "scaleMin": null, "coverageRate": 0.75, "paramPostfix": "", "count": 24, "unitLabel": "&micro;g/m<sup>3</sup>", "startTime": 1311724800}, {"chartTooltipContent": "%y.# %ly o godz. %x", "paramLabel": "Tlenek w\u0119gla", "label": "Tlenek w\u0119gla", "aggType": "A1h", "decimals": 0, "avg": {"min": 370, "avg": 467.39130434783, "max": 670}, "retroCount": 2, "scaleMax": null, "paramId": "co", "unit": "ug/m3", "paramCode": "CO", "thresholds": {"atDecimals": 0, "at": null, "tv": null, "it": null, "itDecimals": 0, "lv": null, "lvDecimals": 0, "tvDecimals": 0}, "ord": 5, "isAvgValid": true, "data": [["1311717600", 530], ["1311721200", 370], ["1311724800", 370], ["1311728400", 430], ["1311732000", 390], ["1311735600", 440], ["1311739200", 440], ["1311742800", 400], ["1311750000", 460], ["1311753600", 510], ["1311757200", 470], ["1311760800", 450], ["1311764400", 400], ["1311768000", 420], ["1311771600", 390], ["1311775200", 400], ["1311778800", 450], ["1311782400", 610], ["1311786000", 650], ["1311789600", 490], ["1311793200", 380], ["1311796800", 550], ["1311800400", 670], ["1311804000", 490], ["1311807600", 490]], "extStartTime": 1311717600, "measType": "auto", "interval": 3600, "thresholdsForAvg": {"min": null, "avg": {"atDecimals": 0, "at": null, "tv": null, "it": null, "itDecimals": 0, "lv": null, "lvDecimals": 0, "tvDecimals": 0}, "max": null}, "scaleMin": null, "coverageRate": 0.75, "paramPostfix": "", "count": 24, "unitLabel": "&micro;g/m<sup>3</sup>", "startTime": 1311724800}, {"chartTooltipContent": "%y.# %ly o godz. %x", "paramLabel": "Tlenek w\u0119gla", "label": "Tlenek w\u0119gla 8h<sup>2)</sup>", "aggType": "sA8h", "decimals": 0, "avg": {"min": null, "avg": null, "max": null}, "retroCount": 2, "scaleMax": null, "paramId": "co", "unit": "ug/m3", "paramCode": "CO", "thresholds": {"atDecimals": 0, "at": null, "tv": null, "it": null, "itDecimals": 0, "lv": 10000, "lvDecimals": 0, "tvDecimals": 0}, "ord": 5, "isAvgValid": false, "data": [], "extStartTime": 1311717600, "measType": "auto", "interval": 3600, "thresholdsForAvg": {"min": null, "avg": null, "max": {"atDecimals": 0, "at": null, "tv": null, "it": null, "itDecimals": 0, "lv": 10000, "lvDecimals": 0, "tvDecimals": 0}}, "scaleMin": null, "coverageRate": 0.75, "paramPostfix": " 8h<sup>2)</sup>", "count": 24, "unitLabel": "&micro;g/m<sup>3</sup>", "startTime": 1311724800}, {"chartTooltipContent": "%y.# %ly o godz. %x", "paramLabel": "Tlenki azotu", "label": "Tlenki azotu", "aggType": "A1h", "decimals": 0, "avg": {"min": "26", "avg": 71.625, "max": "117"}, "retroCount": 2, "scaleMax": null, "paramId": "nox", "unit": "ug/m3", "paramCode": "NO<sub>x</sub>", "thresholds": null, "ord": 3, "isAvgValid": true, "data": [["1311717600", "69"], ["1311721200", "33"], ["1311724800", "40"], ["1311728400", "41"], ["1311732000", "26"], ["1311735600", "34"], ["1311739200", "45"], ["1311742800", "54"], ["1311746400", "86"], ["1311750000", "81"], ["1311753600", "71"], ["1311757200", "62"], ["1311760800", "63"], ["1311764400", "52"], ["1311768000", "77"], ["1311771600", "72"], ["1311775200", "69"], ["1311778800", "92"], ["1311782400", "101"], ["1311786000", "103"], ["1311789600", "98"], ["1311793200", "74"], ["1311796800", "97"], ["1311800400", "117"], ["1311804000", "79"], ["1311807600", "85"]], "extStartTime": 1311717600, "measType": "auto", "interval": 3600, "thresholdsForAvg": {"min": null, "avg": null, "max": null}, "scaleMin": null, "coverageRate": 0.75, "paramPostfix": "", "count": 24, "unitLabel": "&micro;g/m<sup>3</sup>", "startTime": 1311724800}], "charts": [], "viewType": "station", "title": "Dane pomiarowe dla stacji Nowa Huta w dniu 27.07.2011 r.", "dateFormat": "H:00", "unitLabel": "&micro;g/m<sup>3</sup>"}, "success": true}