{"data": {"series": [{"chartTooltipContent": "%y.# %ly o godz. %x", "paramLabel": "Benzen", "label": "Benzen", "aggType": "A1h", "decimals": 1, "avg": {"min": "0", "avg": 0.65833333333333, "max": "2.2"}, "retroCount": 2, "scaleMax": null, "paramId": "bzn", "unit": "ug/m3", "paramCode": "C<sub>6</sub>H<sub>6</sub>", "thresholds": {"atDecimals": 0, "at": null, "tv": null, "it": null, "itDecimals": 0, "lv": null, "lvDecimals": 0, "tvDecimals": 0}, "ord": 6, "isAvgValid": true, "data": [["1156716000", "0.9"], ["1156719600", "0"], ["1156723200", "0"], ["1156726800", "0"], ["1156730400", "0"], ["1156734000", "0"], ["1156737600", "0.2"], ["1156741200", "1.1"], ["1156744800", "1.1"], ["1156748400", "1.1"], ["1156752000", "1.1"], ["1156755600", "0.4"], ["1156759200", "0"], ["1156762800", "0"], ["1156766400", "0"], ["1156770000", "0"], ["1156773600", "0"], ["1156777200", "0"], ["1156780800", "0"], ["1156784400", "0"], ["1156788000", "0.8"], ["1156791600", "1.7"], ["1156795200", "1.9"], ["1156798800", "2.2"], ["1156802400", "2.2"], ["1156806000", "2"]], "extStartTime": 1156716000, "measType": "auto", "interval": 3600, "thresholdsForAvg": {"min": null, "avg": null, "max": null}, "scaleMin": null, "coverageRate": 0.75, "paramPostfix": "", "count": 24, "unitLabel": "&micro;g/m<sup>3</sup>", "startTime": 1156723200}, {"chartTooltipContent": "%y.# %ly o godz. %x", "paramLabel": "Dwutlenek azotu", "label": "Dwutlenek azotu", "aggType": "A1h", "decimals": 0, "avg": {"min": "17", "avg": 30.260869565217, "max": "47"}, "retroCount": 2, "scaleMax": null, "paramId": "no2", "unit": "ug/m3", "paramCode": "NO<sub>2</sub>", "thresholds": {"atDecimals": 0, "at": 400, "tv": null, "it": null, "itDecimals": 0, "lv": 200, "lvDecimals": 0, "tvDecimals": 0}, "ord": 2, "isAvgValid": true, "data": [["1156716000", "32"], ["1156719600", "22"], ["1156723200", "23"], ["1156730400", "27"], ["1156734000", "27"], ["1156737600", "35"], ["1156741200", "39"], ["1156744800", "39"], ["1156748400", "38"], ["1156752000", "26"], ["1156755600", "23"], ["1156759200", "22"], ["1156762800", "25"], ["1156766400", "17"], ["1156770000", "29"], ["1156773600", "30"], ["1156777200", "32"], ["1156780800", "33"], ["1156784400", "31"], ["1156788000", "38"], ["1156791600", "47"], ["1156795200", "32"], ["1156798800", "30"], ["1156802400", "26"], ["1156806000", "27"]], "extStartTime": 1156716000, "measType": "auto", "interval": 3600, "thresholdsForAvg": {"min": null, "avg": null, "max": null}, "scaleMin": null, "coverageRate": 0.75, "paramPostfix": "", "count": 24, "unitLabel": "&micro;g/m<sup>3</sup>", "startTime": 1156723200}, {"chartTooltipContent": "%y.# %ly o godz. %x", "paramLabel": "Dwutlenek siarki", "label": "Dwutlenek siarki<sup>3)</sup>", "aggType": "A1h", "decimals": 1, "avg": {"min": "1", "avg": 8, "max": "18"}, "retroCount": 2, "scaleMax": null, "paramId": "so2", "unit": "ug/m3", "paramCode": "SO<sub>2</sub>", "thresholds": {"atDecimals": 0, "at": 500, "tv": null, "it": null, "itDecimals": 0, "lv": 350, "lvDecimals": 0, "tvDecimals": 0}, "ord": 1, "isAvgValid": true, "data": [["1156716000", "3"], ["1156719600", "2"], ["1156723200", "2"], ["1156730400", "1"], ["1156734000", "2"], ["1156737600", "1"], ["1156741200", "2"], ["1156744800", "5"], ["1156748400", "7"], ["1156752000", "14"], ["1156755600", "15"], ["1156759200", "14"], ["1156762800", "18"], ["1156766400", "13"], ["1156770000", "15"], ["1156773600", "15"], ["1156777200", "14"], ["1156780800", "16"], ["1156784400", "9"], ["1156788000", "5"], ["1156791600", "5"], ["1156795200", "3"], ["1156798800", "3"], ["1156802400", "2"], ["1156806000", "3"]], "extStartTime": 1156716000, "measType": "auto", "interval": 3600, "thresholdsForAvg": {"min": null, "avg": {"atDecimals": 0, "at": null, "tv": null, "it": null, "itDecimals": 0, "lv": 125, "lvDecimals": 0, "tvDecimals": 0}, "max": null}, "scaleMin": null, "coverageRate": 0.75, "paramPostfix": "<sup>3)</sup>", "count": 24, "unitLabel": "&micro;g/m<sup>3</sup>", "startTime": 1156723200}, {"chartTooltipContent": "%y.# %ly o godz. %x", "paramLabel": "Py\u0142 zawieszony PM10", "label": "Py\u0142 zawieszony PM10", "aggType": "A1h", "decimals": 0, "avg": {"min": "13", "avg": 31.625, "max": "56"}, "retroCount": 2, "scaleMax": null, "paramId": "pm10", "unit": "ug/m3", "paramCode": "PM10", "thresholds": {"atDecimals": 0, "at": null, "tv": null, "it": null, "itDecimals": 0, "lv": null, "lvDecimals": 0, "tvDecimals": 0}, "ord": 7, "isAvgValid": true, "data": [["1156716000", "25"], ["1156719600", "33"], ["1156723200", "19"], ["1156726800", "35"], ["1156730400", "27"], ["1156734000", "20"], ["1156737600", "21"], ["1156741200", "34"], ["1156744800", "50"], ["1156748400", "26"], ["1156752000", "43"], ["1156755600", "21"], ["1156759200", "28"], ["1156762800", "14"], ["1156766400", "15"], ["1156770000", "20"], ["1156773600", "13"], ["1156777200", "14"], ["1156780800", "16"], ["1156784400", "34"], ["1156788000", "45"], ["1156791600", "53"], ["1156795200", "56"], ["1156798800", "53"], ["1156802400", "51"], ["1156806000", "51"]], "extStartTime": 1156716000, "measType": "auto", "interval": 3600, "thresholdsForAvg": {"min": null, "avg": {"atDecimals": 0, "at": 300, "tv": null, "it": 200, "itDecimals": 0, "lv": 50, "lvDecimals": 0, "tvDecimals": 0}, "max": null}, "scaleMin": null, "coverageRate": 0.75, "paramPostfix": "", "count": 24, "unitLabel": "&micro;g/m<sup>3</sup>", "startTime": 1156723200}, {"chartTooltipContent": "%y.# %ly o godz. %x", "paramLabel": "Py\u0142 zawieszony PM2.5", "label": "Py\u0142 zawieszony PM2.5", "aggType": "A1h", "decimals": 0, "avg": {"min": null, "avg": null, "max": null}, "retroCount": 2, "scaleMax": null, "paramId": "pm2.5", "unit": "ug/m3", "paramCode": "PM2.5", "thresholds": {"atDecimals": 0, "at": null, "tv": null, "it": null, "itDecimals": 0, "lv": null, "lvDecimals": 0, "tvDecimals": 0}, "ord": 8, "isAvgValid": false, "data": [], "extStartTime": 1156716000, "measType": "auto", "interval": 3600, "thresholdsForAvg": {"min": null, "avg": null, "max": null}, "scaleMin": null, "coverageRate": 0.75, "paramPostfix": "", "count": 24, "unitLabel": "&micro;g/m<sup>3</sup>", "startTime": 1156723200}, {"chartTooltipContent": "%y.# %ly o godz. %x", "paramLabel": "Tlenek azotu", "label": "Tlenek azotu", "aggType": "A1h", "decimals": 0, "avg": {"min": "1", "avg": 13.739130434783, "max": "34"}, "retroCount": 2, "scaleMax": null, "paramId": "no", "unit": "ug/m3", "paramCode": "NO", "thresholds": null, "ord": 14, "isAvgValid": true, "data": [["1156716000", "1"], ["1156719600", "1"], ["1156723200", "1"], ["1156730400", "5"], ["1156734000", "15"], ["1156737600", "17"], ["1156741200", "24"], ["1156744800", "21"], ["1156748400", "17"], ["1156752000", "12"], ["1156755600", "8"], ["1156759200", "7"], ["1156762800", "7"], ["1156766400", "6"], ["1156770000", "8"], ["1156773600", "9"], ["1156777200", "7"], ["1156780800", "7"], ["1156784400", "3"], ["1156788000", "11"], ["1156791600", "29"], ["1156795200", "31"], ["1156798800", "34"], ["1156802400", "22"], ["1156806000", "15"]], "extStartTime": 1156716000, "measType": "auto", "interval": 3600, "thresholdsForAvg": {"min": null, "avg": null, "max": null}, "scaleMin": null, "coverageRate": 0.75, "paramPostfix": "", "count": 24, "unitLabel": "&micro;g/m<sup>3</sup>", "startTime": 1156723200}, {"chartTooltipContent": "%y.# %ly o godz. %x", "paramLabel": "Tlenek w\u0119gla", "label": "Tlenek w\u0119gla", "aggType": "A1h", "decimals": 0, "avg": {"min": 280, "avg": 422.72727272727, "max": 620}, "retroCount": 2, "scaleMax": null, "paramId": "co", "unit": "ug/m3", "paramCode": "CO", "thresholds": {"atDecimals": 0, "at": null, "tv": null, "it": null, "itDecimals": 0, "lv": null, "lvDecimals": 0, "tvDecimals": 0}, "ord": 5, "isAvgValid": true, "data": [["1156716000", 360], ["1156719600", 330], ["1156723200", 280], ["1156730400", 320], ["1156734000", 390], ["1156737600", 470], ["1156741200", 600], ["1156744800", 620], ["1156748400", 560], ["1156752000", 390], ["1156755600", 340], ["1156759200", 320], ["1156762800", 310], ["1156766400", 280], ["1156770000", 310], ["1156773600", 400], ["1156777200", 370], ["1156780800", 390], ["1156784400", 370], ["1156788000", 490], ["1156791600", 590], ["1156795200", 610], ["1156802400", 500], ["1156806000", 390]], "extStartTime": 1156716000, "measType": "auto", "interval": 3600, "thresholdsForAvg": {"min": null, "avg": {"atDecimals": 0, "at": null, "tv": null, "it": null, "itDecimals": 0, "lv": null, "lvDecimals": 0, "tvDecimals": 0}, "max": null}, "scaleMin": null, "coverageRate": 0.75, "paramPostfix": "", "count": 24, "unitLabel": "&micro;g/m<sup>3</sup>", "startTime": 1156723200}, {"chartTooltipContent": "%y.# %ly o godz. %x", "paramLabel": "Tlenek w\u0119gla", "label": "Tlenek w\u0119gla 8h<sup>2)</sup>", "aggType": "sA8h", "decimals": 0, "avg": {"min": null, "avg": null, "max": null}, "retroCount": 2, "scaleMax": null, "paramId": "co", "unit": "ug/m3", "paramCode": "CO", "thresholds": {"atDecimals": 0, "at": null, "tv": null, "it": null, "itDecimals": 0, "lv": 10000, "lvDecimals": 0, "tvDecimals": 0}, "ord": 5, "isAvgValid": false, "data": [], "extStartTime": 1156716000, "measType": "auto", "interval": 3600, "thresholdsForAvg": {"min": null, "avg": null, "max": {"atDecimals": 0, "at": null, "tv": null, "it": null, "itDecimals": 0, "lv": 10000, "lvDecimals": 0, "tvDecimals": 0}}, "scaleMin": null, "coverageRate": 0.75, "paramPostfix": " 8h<sup>2)</sup>", "count": 24, "unitLabel": "&micro;g/m<sup>3</sup>", "startTime": 1156723200}, {"chartTooltipContent": "%y.# %ly o godz. %x", "paramLabel": "Tlenki azotu", "label": "Tlenki azotu", "aggType": "A1h", "decimals": 0, "avg": {"min": "24", "avg": 50.739130434783, "max": "90"}, "retroCount": 2, "scaleMax": null, "paramId": "nox", "unit": "ug/m3", "paramCode": "NO<sub>x</sub>", "thresholds": null, "ord": 3, "isAvgValid": true, "data": [["1156716000", "34"], ["1156719600", "24"], ["1156723200", "24"], ["1156730400", "33"], ["1156734000", "50"], ["1156737600", "60"], ["1156741200", "75"], ["1156744800", "71"], ["1156748400", "63"], ["1156752000", "44"], ["1156755600", "34"], ["1156759200", "33"], ["1156762800", "36"], ["1156766400", "25"], ["1156770000", "40"], ["1156773600", "43"], ["1156777200", "43"], ["1156780800", "44"], ["1156784400", "35"], ["1156788000", "55"], ["1156791600", "90"], ["1156795200", "79"], ["1156798800", "81"], ["1156802400", "59"], ["1156806000", "50"]], "extStartTime": 1156716000, "measType": "auto", "interval": 3600, "thresholdsForAvg": {"min": null, "avg": null, "max": null}, "scaleMin": null, "coverageRate": 0.75, "paramPostfix": "", "count": 24, "unitLabel": "&micro;g/m<sup>3</sup>", "startTime": 1156723200}], "charts": [], "viewType": "station", "title": "Dane pomiarowe dla stacji Nowa Huta w dniu 28.08.2006 r.", "dateFormat": "H:00", "unitLabel": "&micro;g/m<sup>3</sup>"}, "success": true}