{"data": {"series": [{"chartTooltipContent": "%y.# %ly o godz. %x", "paramLabel": "Benzen", "label": "Benzen", "aggType": "A1h", "decimals": 1, "avg": {"min": null, "avg": null, "max": null}, "retroCount": 2, "scaleMax": null, "paramId": "bzn", "unit": "ug/m3", "paramCode": "C<sub>6</sub>H<sub>6</sub>", "thresholds": {"atDecimals": 0, "at": null, "tv": null, "it": null, "itDecimals": 0, "lv": null, "lvDecimals": 0, "tvDecimals": 0}, "ord": 6, "isAvgValid": false, "data": [], "extStartTime": 1188943200, "measType": "auto", "interval": 3600, "thresholdsForAvg": {"min": null, "avg": null, "max": null}, "scaleMin": null, "coverageRate": 0.75, "paramPostfix": "", "count": 24, "unitLabel": "&micro;g/m<sup>3</sup>", "startTime": 1188950400}, {"chartTooltipContent": "%y.# %ly o godz. %x", "paramLabel": "Dwutlenek azotu", "label": "Dwutlenek azotu", "aggType": "A1h", "decimals": 0, "avg": {"min": "16", "avg": 50.166666666667, "max": "67"}, "retroCount": 2, "scaleMax": null, "paramId": "no2", "unit": "ug/m3", "paramCode": "NO<sub>2</sub>", "thresholds": {"atDecimals": 0, "at": 400, "tv": null, "it": null, "itDecimals": 0, "lv": 200, "lvDecimals": 0, "tvDecimals": 0}, "ord": 2, "isAvgValid": true, "data": [["1188943200", "41"], ["1188946800", "37"], ["1188950400", "29"], ["1188954000", "23"], ["1188957600", "16"], ["1188961200", "26"], ["1188964800", "44"], ["1188968400", "51"], ["1188972000", "56"], ["1188975600", "66"], ["1188979200", "58"], ["1188982800", "64"], ["1188986400", "59"], ["1188990000", "59"], ["1188993600", "60"], ["1188997200", "62"], ["1189000800", "59"], ["1189004400", "60"], ["1189008000", "59"], ["1189011600", "67"], ["1189015200", "64"], ["1189018800", "59"], ["1189022400", "52"], ["1189026000", "43"], ["1189029600", "39"], ["1189033200", "29"]], "extStartTime": 1188943200, "measType": "auto", "interval": 3600, "thresholdsForAvg": {"min": null, "avg": null, "max": null}, "scaleMin": null, "coverageRate": 0.75, "paramPostfix": "", "count": 24, "unitLabel": "&micro;g/m<sup>3</sup>", "startTime": 1188950400}, {"chartTooltipContent": "%y.# %ly o godz. %x", "paramLabel": "Py\u0142 zawieszony PM10", "label": "Py\u0142 zawieszony PM10", "aggType": "A1h", "decimals": 0, "avg": {"min": "11", "avg": 28.541666666667, "max": "44"}, "retroCount": 2, "scaleMax": null, "paramId": "pm10", "unit": "ug/m3", "paramCode": "PM10", "thresholds": {"atDecimals": 0, "at": null, "tv": null, "it": null, "itDecimals": 0, "lv": null, "lvDecimals": 0, "tvDecimals": 0}, "ord": 7, "isAvgValid": true, "data": [["1188943200", "35"], ["1188946800", "44"], ["1188950400", "41"], ["1188954000", "39"], ["1188957600", "23"], ["1188961200", "11"], ["1188964800", "11"], ["1188968400", "26"], ["1188972000", "44"], ["1188975600", "36"], ["1188979200", "44"], ["1188982800", "40"], ["1188986400", "43"], ["1188990000", "27"], ["1188993600", "34"], ["1188997200", "26"], ["1189000800", "38"], ["1189004400", "25"], ["1189008000", "19"], ["1189011600", "30"], ["1189015200", "22"], ["1189018800", "38"], ["1189022400", "17"], ["1189026000", "15"], ["1189029600", "15"], ["1189033200", "21"]], "extStartTime": 1188943200, "measType": "auto", "interval": 3600, "thresholdsForAvg": {"min": null, "avg": {"atDecimals": 0, "at": 300, "tv": null, "it": 200, "itDecimals": 0, "lv": 50, "lvDecimals": 0, "tvDecimals": 0}, "max": null}, "scaleMin": null, "coverageRate": 0.75, "paramPostfix": "", "count": 24, "unitLabel": "&micro;g/m<sup>3</sup>", "startTime": 1188950400}, {"chartTooltipContent": "%y.# %ly o godz. %x", "paramLabel": "Py\u0142 zawieszony PM2.5", "label": "Py\u0142 zawieszony PM2.5", "aggType": "A1h", "decimals": 0, "avg": {"min": null, "avg": null, "max": null}, "retroCount": 2, "scaleMax": null, "paramId": "pm2.5", "unit": "ug/m3", "paramCode": "PM2.5", "thresholds": {"atDecimals": 0, "at": null, "tv": null, "it": null, "itDecimals": 0, "lv": null, "lvDecimals": 0, "tvDecimals": 0}, "ord": 8, "isAvgValid": false, "data": [], "extStartTime": 1188943200, "measType": "auto", "interval": 3600, "thresholdsForAvg": {"min": null, "avg": null, "max": null}, "scaleMin": null, "coverageRate": 0.75, "paramPostfix": "", "count": 24, "unitLabel": "&micro;g/m<sup>3</sup>", "startTime": 1188950400}, {"chartTooltipContent": "%y.# %ly o godz. %x", "paramLabel": "Tlenek azotu", "label": "Tlenek azotu", "aggType": "A1h", "decimals": 0, "avg": {"min": "9", "avg": 76.791666666667, "max": "135"}, "retroCount": 2, "scaleMax": null, "paramId": "no", "unit": "ug/m3", "paramCode": "NO", "thresholds": null, "ord": 14, "isAvgValid": true, "data": [["1188943200", "51"], ["1188946800", "37"], ["1188950400", "25"], ["1188954000", "13"], ["1188957600", "9"], ["1188961200", "20"], ["1188964800", "67"], ["1188968400", "115"], ["1188972000", "135"], ["1188975600", "131"], ["1188979200", "98"], ["1188982800", "122"], ["1188986400", "80"], ["1188990000", "84"], ["1188993600", "78"], ["1188997200", "85"], ["1189000800", "72"], ["1189004400", "80"], ["1189008000", "81"], ["1189011600", "98"], ["1189015200", "106"], ["1189018800", "94"], ["1189022400", "100"], ["1189026000", "72"], ["1189029600", "48"], ["1189033200", "30"]], "extStartTime": 1188943200, "measType": "auto", "interval": 3600, "thresholdsForAvg": {"min": null, "avg": null, "max": null}, "scaleMin": null, "coverageRate": 0.75, "paramPostfix": "", "count": 24, "unitLabel": "&micro;g/m<sup>3</sup>", "startTime": 1188950400}, {"chartTooltipContent": "%y.# %ly o godz. %x", "paramLabel": "Tlenek w\u0119gla", "label": "Tlenek w\u0119gla", "aggType": "A1h", "decimals": 0, "avg": {"min": null, "avg": null, "max": null}, "retroCount": 2, "scaleMax": null, "paramId": "co", "unit": "ug/m3", "paramCode": "CO", "thresholds": {"atDecimals": 0, "at": null, "tv": null, "it": null, "itDecimals": 0, "lv": null, "lvDecimals": 0, "tvDecimals": 0}, "ord": 5, "isAvgValid": false, "data": [], "extStartTime": 1188943200, "measType": "auto", "interval": 3600, "thresholdsForAvg": {"min": null, "avg": {"atDecimals": 0, "at": null, "tv": null, "it": null, "itDecimals": 0, "lv": null, "lvDecimals": 0, "tvDecimals": 0}, "max": null}, "scaleMin": null, "coverageRate": 0.75, "paramPostfix": "", "count": 24, "unitLabel": "&micro;g/m<sup>3</sup>", "startTime": 1188950400}, {"chartTooltipContent": "%y.# %ly o godz. %x", "paramLabel": "Tlenek w\u0119gla", "label": "Tlenek w\u0119gla 8h<sup>2)</sup>", "aggType": "sA8h", "decimals": 0, "avg": {"min": null, "avg": null, "max": null}, "retroCount": 2, "scaleMax": null, "paramId": "co", "unit": "ug/m3", "paramCode": "CO", "thresholds": {"atDecimals": 0, "at": null, "tv": null, "it": null, "itDecimals": 0, "lv": 10000, "lvDecimals": 0, "tvDecimals": 0}, "ord": 5, "isAvgValid": false, "data": [], "extStartTime": 1188943200, "measType": "auto", "interval": 3600, "thresholdsForAvg": {"min": null, "avg": null, "max": {"atDecimals": 0, "at": null, "tv": null, "it": null, "itDecimals": 0, "lv": 10000, "lvDecimals": 0, "tvDecimals": 0}}, "scaleMin": null, "coverageRate": 0.75, "paramPostfix": " 8h<sup>2)</sup>", "count": 24, "unitLabel": "&micro;g/m<sup>3</sup>", "startTime": 1188950400}, {"chartTooltipContent": "%y.# %ly o godz. %x", "paramLabel": "Tlenki azotu", "label": "Tlenki azotu", "aggType": "A1h", "decimals": 0, "avg": {"min": "29", "avg": 167.58333333333, "max": "267"}, "retroCount": 2, "scaleMax": null, "paramId": "nox", "unit": "ug/m3", "paramCode": "NO<sub>x</sub>", "thresholds": null, "ord": 3, "isAvgValid": true, "data": [["1188943200", "120"], ["1188946800", "94"], ["1188950400", "68"], ["1188954000", "43"], ["1188957600", "29"], ["1188961200", "57"], ["1188964800", "147"], ["1188968400", "228"], ["1188972000", "262"], ["1188975600", "267"], ["1188979200", "207"], ["1188982800", "250"], ["1188986400", "182"], ["1188990000", "188"], ["1188993600", "180"], ["1188997200", "191"], ["1189000800", "168"], ["1189004400", "182"], ["1189008000", "182"], ["1189011600", "217"], ["1189015200", "226"], ["1189018800", "202"], ["1189022400", "204"], ["1189026000", "154"], ["1189029600", "112"], ["1189033200", "76"]], "extStartTime": 1188943200, "measType": "auto", "interval": 3600, "thresholdsForAvg": {"min": null, "avg": null, "max": null}, "scaleMin": null, "coverageRate": 0.75, "paramPostfix": "", "count": 24, "unitLabel": "&micro;g/m<sup>3</sup>", "startTime": 1188950400}], "charts": [], "viewType": "station", "title": "Dane pomiarowe dla stacji Aleja Krasi\u0144skiego w dniu 05.09.2007 r.", "dateFormat": "H:00", "unitLabel": "&micro;g/m<sup>3</sup>"}, "success": true}