{"data": {"series": [{"chartTooltipContent": "%y.# %ly o godz. %x", "paramLabel": "Benzen", "label": "Benzen", "aggType": "A1h", "decimals": 1, "avg": {"min": null, "avg": null, "max": null}, "retroCount": 2, "scaleMax": null, "paramId": "bzn", "unit": "ug/m3", "paramCode": "C<sub>6</sub>H<sub>6</sub>", "thresholds": {"atDecimals": 0, "at": null, "tv": null, "it": null, "itDecimals": 0, "lv": null, "lvDecimals": 0, "tvDecimals": 0}, "ord": 6, "isAvgValid": false, "data": [], "extStartTime": 1287784800, "measType": "auto", "interval": 3600, "thresholdsForAvg": {"min": null, "avg": null, "max": null}, "scaleMin": null, "coverageRate": 0.75, "paramPostfix": "", "count": 24, "unitLabel": "&micro;g/m<sup>3</sup>", "startTime": 1287792000}, {"chartTooltipContent": "%y.# %ly o godz. %x", "paramLabel": "Dwutlenek azotu", "label": "Dwutlenek azotu", "aggType": "A1h", "decimals": 0, "avg": {"min": "35", "avg": 80.217391304348, "max": "150"}, "retroCount": 2, "scaleMax": null, "paramId": "no2", "unit": "ug/m3", "paramCode": "NO<sub>2</sub>", "thresholds": {"atDecimals": 0, "at": 400, "tv": null, "it": null, "itDecimals": 0, "lv": 200, "lvDecimals": 0, "tvDecimals": 0}, "ord": 2, "isAvgValid": true, "data": [["1287784800", "76"], ["1287788400", "66"], ["1287792000", "57"], ["1287795600", "47"], ["1287799200", "45"], ["1287802800", "41"], ["1287806400", "36"], ["1287810000", "35"], ["1287813600", "48"], ["1287817200", "55"], ["1287824400", "80"], ["1287828000", "86"], ["1287831600", "92"], ["1287835200", "77"], ["1287838800", "91"], ["1287842400", "98"], ["1287846000", "118"], ["1287849600", "113"], ["1287853200", "150"], ["1287856800", "125"], ["1287860400", "136"], ["1287864000", "109"], ["1287867600", "87"], ["1287871200", "59"], ["1287874800", "60"]], "extStartTime": 1287784800, "measType": "auto", "interval": 3600, "thresholdsForAvg": {"min": null, "avg": null, "max": null}, "scaleMin": null, "coverageRate": 0.75, "paramPostfix": "", "count": 24, "unitLabel": "&micro;g/m<sup>3</sup>", "startTime": 1287792000}, {"chartTooltipContent": "%y.# %ly o godz. %x", "paramLabel": "Py\u0142 zawieszony PM10", "label": "Py\u0142 zawieszony PM10", "aggType": "A1h", "decimals": 0, "avg": {"min": "50", "avg": 162.125, "max": "333"}, "retroCount": 2, "scaleMax": null, "paramId": "pm10", "unit": "ug/m3", "paramCode": "PM10", "thresholds": {"atDecimals": 0, "at": null, "tv": null, "it": null, "itDecimals": 0, "lv": null, "lvDecimals": 0, "tvDecimals": 0}, "ord": 7, "isAvgValid": true, "data": [["1287784800", "152"], ["1287788400", "151"], ["1287792000", "137"], ["1287795600", "126"], ["1287799200", "138"], ["1287802800", "133"], ["1287806400", "137"], ["1287810000", "127"], ["1287813600", "133"], ["1287817200", "146"], ["1287820800", "146"], ["1287824400", "132"], ["1287828000", "117"], ["1287831600", "94"], ["1287835200", "62"], ["1287838800", "50"], ["1287842400", "61"], ["1287846000", "81"], ["1287849600", "136"], ["1287853200", "214"], ["1287856800", "223"], ["1287860400", "240"], ["1287864000", "291"], ["1287867600", "327"], ["1287871200", "333"], ["1287874800", "307"]], "extStartTime": 1287784800, "measType": "auto", "interval": 3600, "thresholdsForAvg": {"min": null, "avg": {"atDecimals": 0, "at": 300, "tv": null, "it": 200, "itDecimals": 0, "lv": 50, "lvDecimals": 0, "tvDecimals": 0}, "max": null}, "scaleMin": null, "coverageRate": 0.75, "paramPostfix": "", "count": 24, "unitLabel": "&micro;g/m<sup>3</sup>", "startTime": 1287792000}, {"chartTooltipContent": "%y.# %ly o godz. %x", "paramLabel": "Py\u0142 zawieszony PM2.5", "label": "Py\u0142 zawieszony PM2.5", "aggType": "A1h", "decimals": 0, "avg": {"min": "36", "avg": 138, "max": "295"}, "retroCount": 2, "scaleMax": null, "paramId": "pm2.5", "unit": "ug/m3", "paramCode": "PM2.5", "thresholds": {"atDecimals": 0, "at": null, "tv": null, "it": null, "itDecimals": 0, "lv": null, "lvDecimals": 0, "tvDecimals": 0}, "ord": 8, "isAvgValid": true, "data": [["1287784800", "136"], ["1287788400", "137"], ["1287792000", "123"], ["1287795600", "116"], ["1287799200", "127"], ["1287802800", "123"], ["1287806400", "123"], ["1287810000", "113"], ["1287813600", "115"], ["1287817200", "121"], ["1287820800", "117"], ["1287824400", "102"], ["1287828000", "86"], ["1287831600", "70"], ["1287835200", "48"], ["1287838800", "36"], ["1287842400", "46"], ["1287846000", "59"], ["1287849600", "109"], ["1287853200", "173"], ["1287856800", "187"], ["1287860400", "200"], ["1287864000", "253"], ["1287867600", "291"], ["1287871200", "295"], ["1287874800", "279"]], "extStartTime": 1287784800, "measType": "auto", "interval": 3600, "thresholdsForAvg": {"min": null, "avg": null, "max": null}, "scaleMin": null, "coverageRate": 0.75, "paramPostfix": "", "count": 24, "unitLabel": "&micro;g/m<sup>3</sup>", "startTime": 1287792000}, {"chartTooltipContent": "%y.# %ly o godz. %x", "paramLabel": "Tlenek azotu", "label": "Tlenek azotu", "aggType": "A1h", "decimals": 0, "avg": {"min": "100", "avg": 265.4347826087, "max": "613"}, "retroCount": 2, "scaleMax": null, "paramId": "no", "unit": "ug/m3", "paramCode": "NO", "thresholds": null, "ord": 14, "isAvgValid": true, "data": [["1287784800", "210"], ["1287788400", "178"], ["1287792000", "116"], ["1287795600", "100"], ["1287799200", "113"], ["1287802800", "127"], ["1287806400", "152"], ["1287810000", "160"], ["1287813600", "225"], ["1287817200", "267"], ["1287824400", "267"], ["1287828000", "237"], ["1287831600", "221"], ["1287835200", "128"], ["1287838800", "160"], ["1287842400", "155"], ["1287846000", "299"], ["1287849600", "276"], ["1287853200", "538"], ["1287856800", "464"], ["1287860400", "613"], ["1287864000", "505"], ["1287867600", "362"], ["1287871200", "298"], ["1287874800", "322"]], "extStartTime": 1287784800, "measType": "auto", "interval": 3600, "thresholdsForAvg": {"min": null, "avg": null, "max": null}, "scaleMin": null, "coverageRate": 0.75, "paramPostfix": "", "count": 24, "unitLabel": "&micro;g/m<sup>3</sup>", "startTime": 1287792000}, {"chartTooltipContent": "%y.# %ly o godz. %x", "paramLabel": "Tlenek w\u0119gla", "label": "Tlenek w\u0119gla", "aggType": "A1h", "decimals": 0, "avg": {"min": 1040, "avg": 2571.6666666667, "max": 4900}, "retroCount": 2, "scaleMax": null, "paramId": "co", "unit": "ug/m3", "paramCode": "CO", "thresholds": {"atDecimals": 0, "at": null, "tv": null, "it": null, "itDecimals": 0, "lv": null, "lvDecimals": 0, "tvDecimals": 0}, "ord": 5, "isAvgValid": true, "data": [["1287784800", 2300], ["1287788400", 2150], ["1287792000", 1650], ["1287795600", 1590], ["1287799200", 1730], ["1287802800", 1780], ["1287806400", 1760], ["1287810000", 1700], ["1287813600", 2020], ["1287817200", 2270], ["1287820800", 2470], ["1287824400", 2280], ["1287828000", 2000], ["1287831600", 1670], ["1287835200", 1040], ["1287838800", 1280], ["1287842400", 1170], ["1287846000", 1960], ["1287849600", 2290], ["1287853200", 3840], ["1287856800", 3720], ["1287860400", 4890], ["1287864000", 4900], ["1287867600", 4750], ["1287871200", 4450], ["1287874800", 4510]], "extStartTime": 1287784800, "measType": "auto", "interval": 3600, "thresholdsForAvg": {"min": null, "avg": {"atDecimals": 0, "at": null, "tv": null, "it": null, "itDecimals": 0, "lv": null, "lvDecimals": 0, "tvDecimals": 0}, "max": null}, "scaleMin": null, "coverageRate": 0.75, "paramPostfix": "", "count": 24, "unitLabel": "&micro;g/m<sup>3</sup>", "startTime": 1287792000}, {"chartTooltipContent": "%y.# %ly o godz. %x", "paramLabel": "Tlenek w\u0119gla", "label": "Tlenek w\u0119gla 8h<sup>2)</sup>", "aggType": "sA8h", "decimals": 0, "avg": {"min": null, "avg": null, "max": null}, "retroCount": 2, "scaleMax": null, "paramId": "co", "unit": "ug/m3", "paramCode": "CO", "thresholds": {"atDecimals": 0, "at": null, "tv": null, "it": null, "itDecimals": 0, "lv": 10000, "lvDecimals": 0, "tvDecimals": 0}, "ord": 5, "isAvgValid": false, "data": [], "extStartTime": 1287784800, "measType": "auto", "interval": 3600, "thresholdsForAvg": {"min": null, "avg": null, "max": {"atDecimals": 0, "at": null, "tv": null, "it": null, "itDecimals": 0, "lv": 10000, "lvDecimals": 0, "tvDecimals": 0}}, "scaleMin": null, "coverageRate": 0.75, "paramPostfix": " 8h<sup>2)</sup>", "count": 24, "unitLabel": "&micro;g/m<sup>3</sup>", "startTime": 1287792000}, {"chartTooltipContent": "%y.# %ly o godz. %x", "paramLabel": "Tlenki azotu", "label": "Tlenki azotu", "aggType": "A1h", "decimals": 0, "avg": {"min": "199", "avg": 486.13043478261, "max": "1074"}, "retroCount": 2, "scaleMax": null, "paramId": "nox", "unit": "ug/m3", "paramCode": "NO<sub>x</sub>", "thresholds": null, "ord": 3, "isAvgValid": true, "data": [["1287784800", "398"], ["1287788400", "339"], ["1287792000", "233"], ["1287795600", "199"], ["1287799200", "217"], ["1287802800", "236"], ["1287806400", "268"], ["1287810000", "279"], ["1287813600", "392"], ["1287817200", "464"], ["1287824400", "489"], ["1287828000", "448"], ["1287831600", "430"], ["1287835200", "273"], ["1287838800", "335"], ["1287842400", "335"], ["1287846000", "576"], ["1287849600", "535"], ["1287853200", "972"], ["1287856800", "834"], ["1287860400", "1074"], ["1287864000", "882"], ["1287867600", "642"], ["1287871200", "515"], ["1287874800", "553"]], "extStartTime": 1287784800, "measType": "auto", "interval": 3600, "thresholdsForAvg": {"min": null, "avg": null, "max": null}, "scaleMin": null, "coverageRate": 0.75, "paramPostfix": "", "count": 24, "unitLabel": "&micro;g/m<sup>3</sup>", "startTime": 1287792000}], "charts": [], "viewType": "station", "title": "Dane pomiarowe dla stacji Aleja Krasi\u0144skiego w dniu 23.10.2010 r.", "dateFormat": "H:00", "unitLabel": "&micro;g/m<sup>3</sup>"}, "success": true}