{"data": {"series": [{"chartTooltipContent": "%y.# %ly o godz. %x", "paramLabel": "Benzen", "label": "Benzen", "aggType": "A1h", "decimals": 1, "avg": {"min": null, "avg": null, "max": null}, "retroCount": 2, "scaleMax": null, "paramId": "bzn", "unit": "ug/m3", "paramCode": "C<sub>6</sub>H<sub>6</sub>", "thresholds": {"atDecimals": 0, "at": null, "tv": null, "it": null, "itDecimals": 0, "lv": null, "lvDecimals": 0, "tvDecimals": 0}, "ord": 6, "isAvgValid": false, "data": [], "extStartTime": 1196200800, "measType": "auto", "interval": 3600, "thresholdsForAvg": {"min": null, "avg": null, "max": null}, "scaleMin": null, "coverageRate": 0.75, "paramPostfix": "", "count": 24, "unitLabel": "&micro;g/m<sup>3</sup>", "startTime": 1196208000}, {"chartTooltipContent": "%y.# %ly o godz. %x", "paramLabel": "Dwutlenek azotu", "label": "Dwutlenek azotu", "aggType": "A1h", "decimals": 0, "avg": {"min": "16", "avg": 57.083333333333, "max": "86"}, "retroCount": 2, "scaleMax": null, "paramId": "no2", "unit": "ug/m3", "paramCode": "NO<sub>2</sub>", "thresholds": {"atDecimals": 0, "at": 400, "tv": null, "it": null, "itDecimals": 0, "lv": 200, "lvDecimals": 0, "tvDecimals": 0}, "ord": 2, "isAvgValid": true, "data": [["1196200800", "26"], ["1196204400", "16"], ["1196208000", "23"], ["1196211600", "19"], ["1196215200", "16"], ["1196218800", "19"], ["1196222400", "23"], ["1196226000", "32"], ["1196229600", "47"], ["1196233200", "51"], ["1196236800", "58"], ["1196240400", "53"], ["1196244000", "56"], ["1196247600", "64"], ["1196251200", "65"], ["1196254800", "69"], ["1196258400", "66"], ["1196262000", "83"], ["1196265600", "82"], ["1196269200", "83"], ["1196272800", "86"], ["1196276400", "84"], ["1196280000", "80"], ["1196283600", "76"], ["1196287200", "69"], ["1196290800", "66"]], "extStartTime": 1196200800, "measType": "auto", "interval": 3600, "thresholdsForAvg": {"min": null, "avg": null, "max": null}, "scaleMin": null, "coverageRate": 0.75, "paramPostfix": "", "count": 24, "unitLabel": "&micro;g/m<sup>3</sup>", "startTime": 1196208000}, {"chartTooltipContent": "%y.# %ly o godz. %x", "paramLabel": "Py\u0142 zawieszony PM10", "label": "Py\u0142 zawieszony PM10", "aggType": "A1h", "decimals": 0, "avg": {"min": "11", "avg": 61.583333333333, "max": "164"}, "retroCount": 2, "scaleMax": null, "paramId": "pm10", "unit": "ug/m3", "paramCode": "PM10", "thresholds": {"atDecimals": 0, "at": null, "tv": null, "it": null, "itDecimals": 0, "lv": null, "lvDecimals": 0, "tvDecimals": 0}, "ord": 7, "isAvgValid": true, "data": [["1196200800", "31"], ["1196204400", "19"], ["1196208000", "27"], ["1196211600", "15"], ["1196215200", "11"], ["1196218800", "19"], ["1196222400", "16"], ["1196226000", "23"], ["1196229600", "20"], ["1196233200", "24"], ["1196236800", "36"], ["1196240400", "20"], ["1196244000", "53"], ["1196247600", "35"], ["1196251200", "77"], ["1196254800", "60"], ["1196258400", "50"], ["1196262000", "65"], ["1196265600", "89"], ["1196269200", "86"], ["1196272800", "83"], ["1196276400", "96"], ["1196280000", "121"], ["1196283600", "148"], ["1196287200", "140"], ["1196290800", "164"]], "extStartTime": 1196200800, "measType": "auto", "interval": 3600, "thresholdsForAvg": {"min": null, "avg": {"atDecimals": 0, "at": 300, "tv": null, "it": 200, "itDecimals": 0, "lv": 50, "lvDecimals": 0, "tvDecimals": 0}, "max": null}, "scaleMin": null, "coverageRate": 0.75, "paramPostfix": "", "count": 24, "unitLabel": "&micro;g/m<sup>3</sup>", "startTime": 1196208000}, {"chartTooltipContent": "%y.# %ly o godz. %x", "paramLabel": "Py\u0142 zawieszony PM2.5", "label": "Py\u0142 zawieszony PM2.5", "aggType": "A1h", "decimals": 0, "avg": {"min": null, "avg": null, "max": null}, "retroCount": 2, "scaleMax": null, "paramId": "pm2.5", "unit": "ug/m3", "paramCode": "PM2.5", "thresholds": {"atDecimals": 0, "at": null, "tv": null, "it": null, "itDecimals": 0, "lv": null, "lvDecimals": 0, "tvDecimals": 0}, "ord": 8, "isAvgValid": false, "data": [], "extStartTime": 1196200800, "measType": "auto", "interval": 3600, "thresholdsForAvg": {"min": null, "avg": null, "max": null}, "scaleMin": null, "coverageRate": 0.75, "paramPostfix": "", "count": 24, "unitLabel": "&micro;g/m<sup>3</sup>", "startTime": 1196208000}, {"chartTooltipContent": "%y.# %ly o godz. %x", "paramLabel": "Tlenek azotu", "label": "Tlenek azotu", "aggType": "A1h", "decimals": 0, "avg": {"min": "5", "avg": 110.04166666667, "max": "231"}, "retroCount": 2, "scaleMax": null, "paramId": "no", "unit": "ug/m3", "paramCode": "NO", "thresholds": null, "ord": 14, "isAvgValid": true, "data": [["1196200800", "20"], ["1196204400", "11"], ["1196208000", "11"], ["1196211600", "6"], ["1196215200", "5"], ["1196218800", "5"], ["1196222400", "13"], ["1196226000", "31"], ["1196229600", "71"], ["1196233200", "78"], ["1196236800", "88"], ["1196240400", "86"], ["1196244000", "95"], ["1196247600", "108"], ["1196251200", "105"], ["1196254800", "123"], ["1196258400", "87"], ["1196262000", "152"], ["1196265600", "154"], ["1196269200", "174"], ["1196272800", "174"], ["1196276400", "216"], ["1196280000", "217"], ["1196283600", "231"], ["1196287200", "220"], ["1196290800", "191"]], "extStartTime": 1196200800, "measType": "auto", "interval": 3600, "thresholdsForAvg": {"min": null, "avg": null, "max": null}, "scaleMin": null, "coverageRate": 0.75, "paramPostfix": "", "count": 24, "unitLabel": "&micro;g/m<sup>3</sup>", "startTime": 1196208000}, {"chartTooltipContent": "%y.# %ly o godz. %x", "paramLabel": "Tlenek w\u0119gla", "label": "Tlenek w\u0119gla", "aggType": "A1h", "decimals": 0, "avg": {"min": null, "avg": null, "max": null}, "retroCount": 2, "scaleMax": null, "paramId": "co", "unit": "ug/m3", "paramCode": "CO", "thresholds": {"atDecimals": 0, "at": null, "tv": null, "it": null, "itDecimals": 0, "lv": null, "lvDecimals": 0, "tvDecimals": 0}, "ord": 5, "isAvgValid": false, "data": [], "extStartTime": 1196200800, "measType": "auto", "interval": 3600, "thresholdsForAvg": {"min": null, "avg": {"atDecimals": 0, "at": null, "tv": null, "it": null, "itDecimals": 0, "lv": null, "lvDecimals": 0, "tvDecimals": 0}, "max": null}, "scaleMin": null, "coverageRate": 0.75, "paramPostfix": "", "count": 24, "unitLabel": "&micro;g/m<sup>3</sup>", "startTime": 1196208000}, {"chartTooltipContent": "%y.# %ly o godz. %x", "paramLabel": "Tlenek w\u0119gla", "label": "Tlenek w\u0119gla 8h<sup>2)</sup>", "aggType": "sA8h", "decimals": 0, "avg": {"min": null, "avg": null, "max": null}, "retroCount": 2, "scaleMax": null, "paramId": "co", "unit": "ug/m3", "paramCode": "CO", "thresholds": {"atDecimals": 0, "at": null, "tv": null, "it": null, "itDecimals": 0, "lv": 10000, "lvDecimals": 0, "tvDecimals": 0}, "ord": 5, "isAvgValid": false, "data": [], "extStartTime": 1196200800, "measType": "auto", "interval": 3600, "thresholdsForAvg": {"min": null, "avg": null, "max": {"atDecimals": 0, "at": null, "tv": null, "it": null, "itDecimals": 0, "lv": 10000, "lvDecimals": 0, "tvDecimals": 0}}, "scaleMin": null, "coverageRate": 0.75, "paramPostfix": " 8h<sup>2)</sup>", "count": 24, "unitLabel": "&micro;g/m<sup>3</sup>", "startTime": 1196208000}, {"chartTooltipContent": "%y.# %ly o godz. %x", "paramLabel": "Tlenki azotu", "label": "Tlenki azotu", "aggType": "A1h", "decimals": 0, "avg": {"min": "24", "avg": 224.70833333333, "max": "429"}, "retroCount": 2, "scaleMax": null, "paramId": "nox", "unit": "ug/m3", "paramCode": "NO<sub>x</sub>", "thresholds": null, "ord": 3, "isAvgValid": true, "data": [["1196200800", "56"], ["1196204400", "33"], ["1196208000", "39"], ["1196211600", "28"], ["1196215200", "24"], ["1196218800", "27"], ["1196222400", "42"], ["1196226000", "79"], ["1196229600", "155"], ["1196233200", "169"], ["1196236800", "193"], ["1196240400", "184"], ["1196244000", "200"], ["1196247600", "228"], ["1196251200", "224"], ["1196254800", "255"], ["1196258400", "198"], ["1196262000", "314"], ["1196265600", "317"], ["1196269200", "347"], ["1196272800", "352"], ["1196276400", "415"], ["1196280000", "411"], ["1196283600", "429"], ["1196287200", "406"], ["1196290800", "357"]], "extStartTime": 1196200800, "measType": "auto", "interval": 3600, "thresholdsForAvg": {"min": null, "avg": null, "max": null}, "scaleMin": null, "coverageRate": 0.75, "paramPostfix": "", "count": 24, "unitLabel": "&micro;g/m<sup>3</sup>", "startTime": 1196208000}], "charts": [], "viewType": "station", "title": "Dane pomiarowe dla stacji Aleja Krasi\u0144skiego w dniu 28.11.2007 r.", "dateFormat": "H:00", "unitLabel": "&micro;g/m<sup>3</sup>"}, "success": true}